[1,["ecpdLyjvZBwrvm+cedCcQy","7feGcnRK9D+J8Zz0I6BfbO","3fAS026f1ASL2ExasAsM4P","7a/QZLET9IDreTiBfRn2PD","78n2BHAu9EpZL9whfvjS/n","97zrTrW3BCEKd2nRMm+ooX","c0sE8yIttMrpYyf2fAoSCH","bas0rDJGpOerVXkS/7jgvl","bb7LwhSCtGXYdSJ5fRLzkx","caTneTSw5EzLaUbxo1Yqs8","53ClM0y0dMFY7V5iIXwECT","f7PXpp0g5OKrYylg8J+PAg","61IlQUQN1DNIV6vc1uHNJg","84SIsjWFBAhrW63LxKnjho","69EtfACjBMMIydyFjqe8FI","35k8XkIMZF/p6AbluPe5sy","a3i7rOnpZJiIfjW5G5+Pct","d3MmiWnkVCs7ynBXeR4yIq","e61WG7BUlMebRNj9JkONBm","11s/XASh9GD7ctPw44FI5C","3aCBtnRpdNiKO0nB/WGG/w","01Nk+H22pB1IqVosiAU5rw","edRQddUutMQoet/AzxO20t","c95BF9gXJB4r7gi7z4w8ly","61YKqpgDVPfKs8BzLpbLDz","1988WVCilKk5KHIutymxhk","9cBTF9Z/pPvpLAdJ0/96Ci","bc5zx/RjxCZ5Cu+cCNHyb3","e9M41MHgdOG78VOn5rDQ18","fayk6yIGxAQ7zdYk5FYc+t","97haMIkxxJFJPotfBdWMKM","05v0x2OflOgq49ObOpHoNq","bcLK8cegdFRJam0Zs9BEAF","dcm0qiPSJGQIK4JC6uOSoM","49ld7cTUBLA7c58BEFfJl0","7dBb4e4XpDWYRsveF0gpK5","c7ooKTrExEXZDnzOeTbh7C","34to1fcehGRLyOtBGpfDg8","3emF6mv5lNQ7dvPTiEh6rQ","78hChvQ/JAV4LXmDwZIPe+","8f99LYDXpBq5eIBwVIzl6v","88SGoo/JxKpZVorrHZ1ftr","fedm/gJY1I/IdjuOmLeHzG","34Ib45UsJMGIpe7Sf9YSUy","abaJs48wBCDrSHzt8h0Nvu","f8wC/HQrhIpoxW42EjdkUG","f5HCO9f6RAc6+MoY1IxW0R","942tBdketITJxDOWj/Qbbl","6d9zIEsLFCuI3PcTbpPcsb","c0phiXNVFKwqKqjWBSg0fj","e5/Gz7TQtIgqefiiiKS6Dm","7bt9LddBNMn64GyFlCxdSt","6edXy2Jl1GbYvhZfI2GDSB"],["node","_spriteFrame","_textureSetter","_parent","_defaultClip","_N$skeletonData","tipNode","animItem","hpNode","root","cameraNode","buttleUI","buttleTipUI","weblinkLabel","mapNode","stopNode","propItem","tip3Node","tip2Node","propBossNode2","propBossNode","propDescNode2","propDescNode","gunSpr","boxAnim2","boxAnim","buttleAnim","tipLab2","tipLab","seleteNode","bossNode","playerNode","lockNode","propParent2","playerAniam","maskIcon","bossAniam","propIcon","data"],[["cc.Node",["_name","_groupIndex","_active","_objFlags","_opacity","_prefab","_parent","_components","_contentSize","_children","_trs","_color","_eulerAngles"],-2,4,1,9,5,2,7,5,5],"cc.SpriteFrame",["cc.Node",["_name","_objFlags","_active","_groupIndex","_parent","_components","_prefab","_contentSize","_trs"],-1,1,2,4,5,7],["cc.Widget",["_alignFlags","_originalWidth","_originalHeight","_top","_left","_right","_bottom","node"],-4,1],["cc.Label",["_styleFlags","_string","_fontSize","_lineHeight","_N$horizontalAlign","_N$verticalAlign","_N$overflow","_materials","node"],-4,3,1],["cc.Node",["_name","_groupIndex","_objFlags","_children","_components","_prefab","_contentSize","_parent","_trs"],0,12,9,4,5,1,7],["cc.Sprite",["_sizeMode","node","_materials","_spriteFrame"],2,1,3,6],["sp.Skeleton",["defaultSkin","_preCacheMode","premultipliedAlpha","_animationName","defaultAnimation","loop","_playTimes","node","_materials"],-4,1,3],["cc.RichText",["_N$string","_N$fontSize","_N$lineHeight","_N$horizontalAlign","_N$maxWidth","node"],-2,1],["cc.Node",["_name","_objFlags","_groupIndex","_parent","_components","_prefab","_contentSize","_trs"],0,1,12,4,5,7],["cc.PrefabInfo",["fileId","root"],2,1],["cc.ClickEvent",["_componentId","handler","customEventData","target"],0,1],["cc.Prefab",["_name"],2],["cc.BlockInputEvents",["node"],3,1],["b4e4aZXGdBAr4tMw77uduDX",["node","propItem","animItem","stopNode","mapNode","weblinkLabel","buttleTipUI","buttleUI","cameraNode","tipNode"],3,1,1,1,1,1,1,1,1,1,1],["d8featdr7ZHOKOyZnhozyb+",["node","playerNode","bossNode","seleteNode","tipLab","tipLab2","buttleAnim","boxAnim","boxAnim2","gunSprArr","gunSpr","propDescNode","propDescNode2","propBossNode","propBossNode2","tip2Node","tip3Node"],3,1,1,1,1,1,1,1,1,1,3,1,1,1,1,1,1,1],["2bd6efAvGJE6r3vRwwpAI3n",["node","hpNode","playerAniam","propParent2","lockNode","tipNode"],3,1,1,1,1,1,1],["cc.Button",["node","clickEvents"],3,1,9],["f8a83Fe0VFPtr9149bjMwNc",["node","hpNode","bossAniam","bossAniamArr","maskIcon"],3,1,1,1,3,1],["cc.LabelOutline",["_width","node","_color"],2,1,5],["cc.LabelShadow",["_blur","node","_color","_offset"],2,1,5,5],["cc.Animation",["playOnLoad","node","_clips","_defaultClip"],2,1,3,6],["6a4a2sQ6vlAHYB1t8/StTCu",["node","propIcon"],3,1,1],["72ab9Rbd0hOiJ/AU3Sz6z8b",["node","animItem"],3,1,1],["08526eaTJpCXYM9VKuRXAnP",["node","clickEvents"],3,1,9],["cc.Camera",["_cullingMask","_nearClip","node"],1,1],["cc.AnimationClip",["_name","_duration","wrapMode","curveData"],-1]],[[10,0,1,2],[6,1,2,3,1],[0,0,1,6,7,5,8,10,3],[0,0,6,7,5,8,10,2],[17,0,1,1],[11,0,1,3,3],[3,0,7,2],[4,1,2,3,0,4,5,8,7,7],[13,0,1],[6,1,2,1],[0,0,9,5,2],[0,0,6,7,5,11,8,10,2],[6,0,1,2,3,2],[11,0,1,2,3,4],[4,1,2,3,0,8,7,5],[19,0,1,2,2],[0,0,1,9,7,5,8,10,3],[0,0,1,6,5,3],[0,0,1,6,9,7,5,8,10,3],[0,0,6,7,5,8,2],[3,0,1,2,7,4],[20,0,1,2,3,2],[21,0,1,2,3,2],[26,0,1,2,3,5],[0,0,3,2,1,6,9,7,5,8,5],[0,0,2,1,6,9,7,5,8,4],[0,0,3,2,6,9,7,5,8,10,4],[0,0,6,9,7,5,8,10,2],[0,0,1,6,7,5,8,3],[0,0,4,6,7,5,8,10,3],[0,0,1,6,9,7,5,10,3],[0,0,1,6,7,5,10,3],[0,0,2,6,7,5,8,10,3],[2,0,1,2,4,5,6,7,8,4],[2,0,4,5,6,7,8,2],[2,0,3,4,5,6,7,3],[3,7,1],[4,1,0,4,5,8,7,5],[4,1,2,3,0,4,5,6,8,7,8],[24,0,1,1],[7,0,4,1,5,2,3,6,7,8,8],[7,0,4,1,2,3,7,8,6],[7,0,1,5,2,3,6,7,8,7],[8,0,1,5,3],[8,0,3,1,4,2,5,6],[12,0,2],[0,0,3,6,5,3],[0,0,6,5,2],[0,0,2,6,9,7,5,8,3],[0,0,1,6,9,7,5,8,3],[0,0,3,2,6,9,7,5,8,4],[0,0,2,6,9,5,3],[0,0,3,6,9,5,3],[0,0,6,9,7,5,10,2],[0,0,3,2,4,6,9,7,5,8,10,5],[0,0,2,1,9,7,5,4],[0,0,2,1,9,7,5,8,10,4],[0,0,3,1,6,9,5,4],[0,0,1,6,9,5,3],[0,0,1,6,7,5,11,8,10,3],[0,0,1,6,7,5,8,10,12,3],[5,0,1,3,4,5,6,3],[5,0,1,7,3,4,5,8,3],[5,0,2,1,7,3,4,5,6,4],[9,0,1,3,4,5,6,7,3],[9,0,2,3,4,5,6,7,3],[2,0,4,5,6,2],[2,0,1,4,5,6,7,3],[2,0,4,5,6,7,2],[2,0,2,4,5,6,7,8,3],[3,0,4,5,3,6,1,2,7,8],[3,0,3,7,3],[3,4,5,3,6,1,2,7,7],[14,0,1,2,3,4,5,6,7,8,9,1],[10,1,1],[15,0,1,2,3,4,5,6,7,8,9,10,11,12,13,14,15,16,1],[16,0,1,2,3,4,5,1],[18,0,1,2,3,4,1],[4,1,2,3,0,4,5,7,7],[4,2,3,0,4,5,6,8,7,7],[22,0,1,1],[23,0,1,1],[25,0,1,2,3],[8,0,1,2,5,4]],[[[{"name":"demon_handcuff02","rect":[0,0,189,110],"offset":[0,0],"originalSize":[189,110],"capInsets":[0,0,0,0]}],[1],0,[0],[2],[11]],[[{"name":"gun2","rect":[0,0,187,102],"offset":[0,0],"originalSize":[187,102],"capInsets":[0,0,0,0]}],[1],0,[0],[2],[12]],[[{"name":"lp_em","rect":[0,0,150,79],"offset":[0,0],"originalSize":[150,79],"capInsets":[0,0,0,0]}],[1],0,[0],[2],[13]],[[{"name":"yz_dl_gb","rect":[0,0,74,78],"offset":[0,0],"originalSize":[74,78],"capInsets":[0,0,0,0]}],[1],0,[0],[2],[14]],[[{"name":"bg","rect":[0,0,1076,1910],"offset":[0,0],"originalSize":[1076,1910],"capInsets":[0,0,0,0]}],[1],0,[0],[2],[15]],[[{"name":"emlp_sm1","rect":[0,0,30,29],"offset":[0,0],"originalSize":[30,29],"capInsets":[0,0,0,0]}],[1],0,[0],[2],[16]],[[{"name":"lp_dj","rect":[0,0,575,574],"offset":[0,0],"originalSize":[575,574],"capInsets":[0,0,0,0]}],[1],0,[0],[2],[17]],[[{"name":"zhidaokuang","rect":[0,1,204,172],"offset":[0,0],"originalSize":[204,174],"capInsets":[0,0,0,0]}],[1],0,[0],[2],[18]],[[{"name":"lp_em02","rect":[4,2,177,109],"offset":[0,0.5],"originalSize":[185,114],"capInsets":[0,0,0,0]}],[1],0,[0],[2],[19]],[[[45,"DMD_UIGame"],[16,"DMD_UIGame",8,[-14,-15,-16,-17,-18,-19,-20,-21,-22,-23,-24],[[6,45,-2],[8,-3],[73,-13,-12,-11,-10,-9,-8,-7,-6,-5,-4]],[74,-1],[5,750,1334],[375,667,0,0,0,0,1,1,1,1]],[61,"central",8,[[-42,-43,-44,[46,"anima2",512,-45,[0,"52+NQh1VtAAImR6G6Z/R3W",1]],-46,-47,-48,-49,[47,"anima",-50,[0,"2cV5rN429IbbWfNAZnqtTX",1]]],1,1,1,4,1,1,1,1,4],[[6,45,-25],[75,-41,-40,-39,-38,-37,-36,-35,-34,-33,[84,85],-32,-31,-30,-29,-28,-27,-26]],[0,"3bFZWUs2ZI3KWUdh5hthOu",1],[5,750,1334]],[62,"player",8,2,[[[17,"prop",8,-57,[0,"db9iwg2TRAlbGLmqAM13Xg",1]],-58,-59,-60,-61,-62],4,1,1,1,1,1],[[76,-56,-55,-54,-53,-52,-51]],[0,"94sx8CZPtI9rBgXNXKCldU",1],[37,0,0,0,0,0,1,1,1,1]],[48,"propUse",false,1,[-67,-68,-69,-70,-71,-72],[[8,-63],[6,45,-64],[1,-65,[98],99],[4,-66,[[5,"2bd6efAvGJE6r3vRwwpAI3n","onClickUseProp",3]]]],[0,"97yk163KBLjqF04XRZx6Pr",1],[5,750,1334]],[49,"root",8,1,[-74,-75,2,-76,-77,-78,-79],[[20,45,300,200,-73]],[0,"a26jCCdGRCMr1B3OeaZV7N",1],[5,750,1334]],[50,"tip",512,false,5,[-83,-84,-85,-86],[[8,-80],[6,45,-81],[4,-82,[[5,"b4e4aZXGdBAr4tMw77uduDX","onClickCloseTipNode",1]]]],[0,"adxZsk1YBP1pcMaQdJh9kV",1],[5,750,1334]],[24,"propBossUse",512,false,8,1,[-90,-91,-92],[[9,-87,[104]],[20,45,1076,1910,-88],[4,-89,[[5,"d8featdr7ZHOKOyZnhozyb+","onClickCloseBossUI",2]]]],[0,"80rJi4XwRD9qKAl4OAYJic",1],[5,750,1334]],[63,"Boss",512,8,2,[[-97,-98,-99,[17,"prop",8,-100,[0,"e51gaEshNH8riFf15Xt3r4",1]]],1,1,1,4],[[77,-96,-95,-94,[61,62],-93]],[0,"f2H8IFXkhLybIE9OFZapfL",1],[5,750,1334.21]],[25,"propNullButtle",false,8,1,[-103,-104,-105],[[70,45,-163,-163,-288,-288,1076,1910,-101],[4,-102,[[5,"d8featdr7ZHOKOyZnhozyb+","onClickBossNullButtleTip",2]]]],[0,"eccGE9dDpEpJMEHXkShREP",1],[5,1076,1910]],[24,"buttleTipUI",512,false,8,1,[-108,-109,-110],[[6,45,-106],[8,-107]],[0,"5au23MhrZJMbliB8CtNJk+",1],[5,750,1334]],[25,"stopNode",false,8,1,[-114,-115],[[6,45,-111],[8,-112],[4,-113,[[5,"b4e4aZXGdBAr4tMw77uduDX","onClickCloseSet",1]]]],[0,"cag6l7BY1AhI0nqQ1QXBIy",1],[5,750,1334]],[10,"no",[-116,-117,-118,-119,-120],[0,"66kjtZIjRFPaUaeFbKnNgE",1]],[10,"xue",[-121,-122,-123,-124,-125],[0,"9b57J3Eo1MgpYr7jBPIn1p",1]],[10,"no",[-126,-127,-128,-129,-130],[0,"45FtFxeYlFF71J6VR2ebbu",1]],[10,"xue",[-131,-132,-133,-134,-135],[0,"a4cYYU4c5D67NGTt9XJbNX",1]],[3,"weblinkLabel",5,[[7,"通关第3章解锁本玩法",52,50.3,1,1,1,-136,[117]],[71,1,83.25,-137],[15,4,-138,[4,4278190080]],[21,4,-139,[4,4278190080],[0,0,0]]],[0,"32cPoU8S5HLKrZb9jsM2Ue",1],[5,504.92,71],[0,566,0,0,0,0,1,0.5,0.5,0.5]],[26,"tip2",512,false,3,[-141,-142],[[1,-140,[9],10]],[0,"b9L4F5oitCRI4+HCpged49",1],[5,227,103],[-204,285,0,0,0,0,1,1,1,1]],[26,"tip3",512,false,3,[-144,-145],[[1,-143,[13],14]],[0,"32ttU49H5O5p1kDLc6HKTS",1],[5,227,103],[-204,285,0,0,0,0,1,1,1,1]],[16,"playerHp",8,[14,15],[[1,-146,[57],58]],[0,"3cO6RO3cRIIakTB+nnJXxj",1],[5,224,52],[-1,-575.812,0,0,0,0,1,1,1,1]],[16,"bossHp",8,[12,13],[[1,-147,[35],36]],[0,"687DCDzCxBT51nQfpokII/",1],[5,224,52],[222,200,0,0,0,0,1,1,1,1]],[51,"seletePlay",false,5,[-148,-149,-150],[0,"89/WFK0ppNCa5EQuy5l5tj",1]],[18,"lp_em",8,21,[-154],[[1,-151,[67],68],[4,-152,[[13,"d8featdr7ZHOKOyZnhozyb+","onClickSeletePlay2","2",2]]],[22,true,-153,[70],69]],[0,"dcdrvAFPNHZYNJxaVRjCBY",1],[5,150,79],[6,37,0,0,0,0,1,1,1,0]],[18,"lp_em",8,21,[-158],[[1,-155,[73],74],[4,-156,[[13,"d8featdr7ZHOKOyZnhozyb+","onClickSeletePlay2","3",2]]],[22,true,-157,[76],75]],[0,"d6Drv3SPNB0bgezoKG9QKs",1],[5,190,100],[6,-139,0,0,0,0,1,1,1,0]],[18,"lp_n",8,21,[-162],[[1,-159,[79],80],[4,-160,[[13,"d8featdr7ZHOKOyZnhozyb+","onClickSeletePlay2","1",2]]],[22,true,-161,[82],81]],[0,"dbgTkNNrVLpK+iOvHhS+6F",1],[5,137,144],[2,-357,0,0,0,0,1,1,1,0]],[52,"tip",512,3,[-163,-164],[0,"52yeWnbxJCm5RjF/5GzS99",1]],[53,"topNode2",1,[-166,-167],[[6,1,-165]],[0,"1ez1eyLjBOr7dC0pfoKpct",1],[0,667,0,0,0,0,1,1,1,1]],[54,"propDesc",512,false,210,1,[-169],[[12,0,-168,[86],87]],[0,"c4f+atvT5AoYi6Uc+Cr+wM",1],[5,500,200],[0,-395.068,0,0,0,0,1,1,1,1]],[27,"button",4,[-172],[[4,-170,[[5,"2bd6efAvGJE6r3vRwwpAI3n","onClickUseProp",3]]],[1,-171,[93],94]],[0,"01G0kcCy9I84AECEOC58IB",1],[5,217,75],[-137,-407,0,0,0,0,1,1,1,0]],[27,"button",4,[-175],[[4,-173,[[13,"2bd6efAvGJE6r3vRwwpAI3n","onClickUseProp","1",3]]],[1,-174,[96],97]],[0,"a7b1pmVaNDxbt/z7MZOplA",1],[5,217,75],[137,-407,0,0,0,0,1,1,1,0]],[55,"propItem",false,8,[-178],[[80,-177,-176]],[0,"19HT9FmSZFc5GvzPdadbJF",1]],[56,"animaNode",false,8,[-181],[[81,-180,-179]],[0,"01MDRYtedF7rRHv6EOJPq3",1],[5,750,1334],[0,81,0,0,0,0,1,1,1,1]],[28,"bg",8,1,[[1,-182,[0],1],[72,374,374,666,666,2,2,-183]],[0,"d3Xss7zgFLgpnwqF/39byB",1],[5,1076,1910]],[64,"gun",512,2,[[-184,[4,-185,[[5,"d8featdr7ZHOKOyZnhozyb+","onClickSeletePlay",2]]]],1,4],[0,"98oSUAuTtKX467fhko7Cbg",1],[5,181,111],[0,-68,0,0,0,0,1,1,1,0]],[65,"icon",8,8,[[-186,[4,-187,[[5,"2bd6efAvGJE6r3vRwwpAI3n","startAttack",3]]]],1,4],[0,"b9Howhu21DGIdq99JvQ5Xd",1],[5,107,146],[0,205,0,0,0,0,1,1,1,1]],[3,"lock",3,[[1,-188,[5],6]],[0,"2bn1t8mjJNpbtksI0HcuAn",1],[5,189,110],[236.39,-545,0,0,0,0,1,1,1,1]],[57,"hp",512,8,2,[20,19],[0,"f2lq2Vf/pEzqruPvZbsnIN",1]],[3,"title",28,[[7,"容我想想",80,80,1,1,1,-189,[92]],[21,0,-190,[4,4278190080],[0,0,-6]]],[0,"d0Oq9yqN9ETLKVVKP2ROzU",1],[5,320,100.8],[0,0,0,0,0,0,1,0.5,0.5,0.5]],[3,"title",29,[[7,"使用",80,80,1,1,1,-191,[95]],[21,0,-192,[4,4278190080],[0,0,-6]]],[0,"8bgFxFXl1E8pjtm+fAUZTX",1],[5,160,100.8],[0,0,0,0,0,0,1,0.5,0.5,0.5]],[11,"labText",7,[[37,"点击继续",1,1,1,-193,[103]],[15,6,-194,[4,4278190080]]],[0,"1cm3nmww1OA6TifW+pA2iY",1],[4,4278254335],[5,172,62.4],[206.312,-454.646,0,0,0,0,1,0.5,0.5,0.5]],[29,"bg",210,9,[[12,0,-195,[105],106],[4,-196,[[5,"d8featdr7ZHOKOyZnhozyb+","onClickBossNullButtleTip",2]]]],[0,"c7VbXwIR5Dl6vffBFNvPQR",1],[5,500,200],[0,-393.415,0,0,0,0,1,1,1,1]],[11,"labText",9,[[37,"点击继续",1,1,1,-197,[108]],[15,6,-198,[4,4278190080]]],[0,"9dl/v+Y/lDMrhs8u1wkicE",1],[4,4278254335],[5,172,62.4],[206.312,-452.993,0,0,0,0,1,0.5,0.5,0.5]],[58,"Pool",8,5,[30,31],[0,"barP6pbmRNiK/b73ViAIyB",1]],[28,"bg",8,10,[[1,-199,[118],119],[20,45,750,1334,-200]],[0,"d9ecUhYTNCFJnwDeJ1tzwK",1],[5,750,1334]],[2,"buttle",8,10,[[1,-201,[122],123]],[0,"fbXA+7C5tJT4KWqdS8dqoU",1],[5,144,142],[-2,168,0,0,0,0,1,1,1,1]],[30,"topNode1",8,1,[-203],[[6,1,-202]],[0,"4fkcCVfrZIIb5ZDR+ejoU/",1],[0,667,0,0,0,0,1,1,1,1]],[2,"yz_zd_ks",8,45,[[1,-204,[124],125],[39,-205,[[5,"b4e4aZXGdBAr4tMw77uduDX","onClickOpenSet",1]]]],[0,"b93QiVx2xFja6XiU2c2cG+",1],[5,51,52],[-325,-99,0,0,0,0,1,1,1,0]],[30,"topNode",8,11,[-207],[[6,1,-206]],[0,"4aI6d3tRpEDavJ24kdQ/pJ",1],[0,667,0,0,0,0,1,1,1,1]],[2,"yz_dl_gb",8,47,[[1,-208,[126],127],[39,-209,[[5,"b4e4aZXGdBAr4tMw77uduDX","onClickExitApp",1]]]],[0,"e00hJnEKBIAIQEnELWEBGE",1],[5,74,78],[-325,-99,0,0,0,0,1,1,1,0]],[59,"title",8,11,[[7,"暂停中\n点击任意区域继续",64,76,1,1,1,-210,[128]],[15,6,-211,[4,4278190080]]],[0,"51Ag1sMnND37ZDlVNaYM0r",1],[4,4281999093],[5,524,183.76],[0,-80,0,0,0,0,1,0.5,0.5,1]],[66,"Camera",1,[-212],[0,"9f+tEStSdCwZ450dkTrEqo",1]],[82,256,0.1,50],[31,"topNode",8,5,[[36,-213]],[0,"dcRV3ytB9I95bMAg9pyjTS",1],[0,667,0,0,0,0,1,1,1,1]],[31,"bottomNode",8,5,[[36,-214]],[0,"e7+vxXTcVBc5C19IsFYF1J",1],[0,-667,0,0,0,0,1,1,1,1]],[9,33,[2]],[9,34,[3]],[67,"anim",512,3,[-215],[0,"6eIlnW3MBLqImhXs1XUWFg",1],[5,750,1334]],[40,"default","gun8",0,false,false,"gun8",1,56,[4]],[32,"tipLab2",false,25,[[43,"<b>选择 <color=#FF0000>手枪</c>  或 <color=#00ff00>道具</c></b>",36,-216]],[0,"ca4jVDaV9FLb7M86nkXibY",1],[5,292.01,50.4],[-37,-463.471,0,0,0,0,1,1,1,1]],[32,"tipLab3",false,25,[[43,"<b>选择 <color=#FF0000>射击目标</c>  </b>",36,-217]],[0,"f1+jYxH2xEAJcPw3vamB8l",1],[5,246,50.4],[-37,-463.471,0,0,0,0,1,1,1,1]],[3,"tipLab2",17,[[14,"空弹？运气不错！",48,48,1,-218,[7]]],[0,"e0q47ie4pLRqq2ixbduvnU",1],[5,384,60.48],[0,24,0,0,0,0,1,0.5,0.5,1]],[11,"tipLab2",17,[[14,"（额外行动一次）",48,48,1,-219,[8]]],[0,"99OossPIlAjYPhX/txjh85",1],[4,4281332735],[5,384,60.48],[0,-12,0,0,0,0,1,0.5,0.5,1]],[3,"tipLab2",18,[[14,"没有实弹怎么玩！",48,48,1,-220,[11]]],[0,"62P7mv3x5Ny5RFZP1UuWGP",1],[5,384,60.48],[0,24,0,0,0,0,1,0.5,0.5,1]],[11,"tipLab2",18,[[14,"（重新装弹）",48,48,1,-221,[12]]],[0,"42CELrhzNHgqCzacCV+7z/",1],[4,4281332735],[5,288,60.48],[0,-12,0,0,0,0,1,0.5,0.5,1]],[2,"lp_hp",8,12,[[1,-222,[15],16]],[0,"bajT6kn0pMtrUQJFUrVxZY",1],[5,30,29],[-60,0,0,0,0,0,1,1,1,1]],[2,"lp_hp",8,12,[[1,-223,[17],18]],[0,"57DshsyglJ0JG2PUxaKv3/",1],[5,30,29],[-25,0,0,0,0,0,1,1,1,1]],[2,"lp_hp",8,12,[[1,-224,[19],20]],[0,"47RO0OVOFJ+7iElbHO/Sav",1],[5,30,29],[9,0,0,0,0,0,1,1,1,1]],[2,"lp_hp",8,12,[[1,-225,[21],22]],[0,"1fJpKnCEZKToCIfHTY4ASK",1],[5,30,29],[46,0,0,0,0,0,1,1,1,1]],[2,"lp_hp",8,12,[[1,-226,[23],24]],[0,"96IxR2H+JEh6WuNbdgZ+N1",1],[5,30,29],[81,0,0,0,0,0,1,1,1,1]],[2,"lp_hp",8,13,[[1,-227,[25],26]],[0,"31QX1+UyZDC7BRECSyjHTQ",1],[5,30,29],[-60,0,0,0,0,0,1,1,1,1]],[2,"lp_hp",8,13,[[1,-228,[27],28]],[0,"7c2TqyrDNL/YmUpSeHY7nF",1],[5,30,29],[-25,0,0,0,0,0,1,1,1,1]],[2,"lp_hp",8,13,[[1,-229,[29],30]],[0,"9302ujoLNCcqoHnzjgZTvo",1],[5,30,29],[9,0,0,0,0,0,1,1,1,1]],[2,"lp_hp",8,13,[[1,-230,[31],32]],[0,"51VKAOUOlI4qu1Ua2a14lm",1],[5,30,29],[46,0,0,0,0,0,1,1,1,1]],[2,"lp_hp",8,13,[[1,-231,[33],34]],[0,"3eHNrPmCZJM7SXB48I3v4m",1],[5,30,29],[81,0,0,0,0,0,1,1,1,1]],[2,"lp_hp",8,14,[[1,-232,[37],38]],[0,"1bXkjHNBJMC7+NHdPkcGE+",1],[5,30,29],[-79,4,0,0,0,0,1,1,1,1]],[2,"lp_hp",8,14,[[1,-233,[39],40]],[0,"betkEKh2hH24qjz9eZzZFe",1],[5,30,29],[-39,4,0,0,0,0,1,1,1,1]],[2,"lp_hp",8,14,[[1,-234,[41],42]],[0,"56ATCNeytPqaccixnpnaQp",1],[5,30,29],[1,4,0,0,0,0,1,1,1,1]],[2,"lp_hp",8,14,[[1,-235,[43],44]],[0,"18W/ZiMsJDLIz4l/EJNzZK",1],[5,30,29],[42,4,0,0,0,0,1,1,1,1]],[2,"lp_hp",8,14,[[1,-236,[45],46]],[0,"3fXM7wAdlPPL6e8vRhjJ9s",1],[5,30,29],[81,5,0,0,0,0,1,1,1,1]],[2,"lp_hp",8,15,[[1,-237,[47],48]],[0,"fc+csFpD5IhqL1r2QOp3s4",1],[5,30,29],[-79,4,0,0,0,0,1,1,1,1]],[2,"lp_hp",8,15,[[1,-238,[49],50]],[0,"d1k4706JRCu5tZIEKlclN8",1],[5,30,29],[-39,4,0,0,0,0,1,1,1,1]],[2,"lp_hp",8,15,[[1,-239,[51],52]],[0,"a0LvlWekxOZ72BV5HKQlpY",1],[5,30,29],[1,4,0,0,0,0,1,1,1,1]],[2,"lp_hp",8,15,[[1,-240,[53],54]],[0,"7d7bAVOqdKr4eUalcYPzIb",1],[5,30,29],[42,4,0,0,0,0,1,1,1,1]],[2,"lp_hp",8,15,[[1,-241,[55],56]],[0,"07lQEQ9CZO35eM+eFNLWRb",1],[5,30,29],[81,5,0,0,0,0,1,1,1,1]],[17,"prop2",8,2,[0,"6bX+Oi1h1Co5qac5ULc2Xb",1]],[68,"anim",8,[-242],[0,"e0scg4BIJFsptcg2v9KZHo",1],[5,750,1334]],[41,"default","approach",0,false,"approach",85,[59]],[69,"box2",false,8,[-243],[0,"98vTXpA8lISomWzsjaZJai",1],[5,750,1334],[18,72,0,0,0,0,1,1,1,1]],[42,"default",0,false,false,"open",1,87,[60]],[33,"box",512,false,2,[-244],[0,"95Qz8Za2tJ4omGeDnAhzHU",1],[5,750,1334],[0,-389,0,0,0,0,1,1,1,1]],[40,"default","open",0,false,false,"open",1,89,[63]],[33,"buttle",512,false,2,[-245],[0,"15Vr9a225KfZbJ0K5aGM+Z",1],[5,750,1334],[166,-22,0,0,0,0,1,1,1,1]],[42,"default",0,false,false,"1-1",1,91,[64]],[19,"lp_em02",22,[[1,-246,[65],66]],[0,"04RxQk+6RJY5rTV4TzMJon",1],[5,177,109]],[19,"lp_fx02",23,[[1,-247,[71],72]],[0,"b64j5HTIxOh7LC0poYyAdv",1],[5,219,129]],[19,"lp_fx02",24,[[1,-248,[77],78]],[0,"d2yKfCSiZMnqhDAFfjN6NW",1],[5,163,172]],[78,"你的回合",92,92,1,1,1,[83]],[34,"tipLab",26,[96],[0,"d6c7SLapBNzax1GoPzA1PT",1],[5,368,115.92],[0,-144,0,0,0,0,1,0.5,0.5,1]],[34,"tipLab2",26,[-249],[0,"53Zefy+rxF6J+tGT2OL8+I",1],[5,613.4200000000001,60.480000000000004],[0,-197.906,0,0,0,0,1,0.5,0.5,1]],[83,"<b>剩余子弹     实弹: <color=#FF0000>0</c>      空：<color=#00ff00>0</c>",48,48,98],[3,"labDesc",27,[[44,"50%概率回两格血，50%概率扣一格血",1,80,800,80,-250]],[0,"0a7QBfCrhMLouoqmcyKYL1",1],[5,800,180.79999999999998],[0,0,0,0,0,0,1,0.5,0.5,1]],[3,"xiaokuang",4,[[12,0,-251,[88],89]],[0,"4aFCIqFF1DP7liIUlmH2ll",1],[5,600,150],[0,-212,0,0,0,0,1,1,1,1]],[3,"icon",4,[[9,-252,[90]]],[0,"fbAdPXRHpNLaIZtW3cvKVA",1],[5,295,156],[0,155.416,0,0,0,0,1,0.8,0.8,0.8]],[3,"title",4,[[38,"偷窃",80,80,1,1,1,3,-253,[91]]],[0,"91dJOLvcdKGL3b/rzzzWgV",1],[5,878.78,100.8],[0,-87,0,0,0,0,1,0.5,0.5,0.5]],[3,"desc",4,[[44,"50%概率回两格血，50%概率扣一格血",1,56,800,80,-254]],[0,"7bQpIJ7XlNPJISDPSuS1Id",1],[5,800,180.79999999999998],[0,-214.115,0,0,0,0,1,0.5,0.5,0.5]],[29,"bg",210,7,[[12,0,-255,[100],101]],[0,"33VPmYt19C/b2lkJOkKcZz",1],[5,500,200],[0,-395.068,0,0,0,0,1,1,1,1]],[3,"labDesc",7,[[79,64,80,1,1,1,3,-256,[102]]],[0,"cdGh8MSMBAY6y8/RFQXezC",1],[5,878.78,100.8],[0,-395.068,0,0,0,0,1,0.5,0.5,0.5]],[3,"labDesc",9,[[38,"Boss赌到空弹，额外行动一回合",64,80,1,1,1,3,-257,[107]]],[0,"e3o7ej/JVLJqXxGCxd2Dz7",1],[5,878.78,180.79999999999998],[0,-393.415,0,0,0,0,1,0.5,0.5,0.5]],[35,"icon",8,30,[-258],[0,"ffMTXX1tBGGJ23H6BjsX5i",1],[5,71,72]],[9,108,[109]],[35,"anim",8,31,[-259],[0,"81h5vuWMxMFZZ3TUO1CP0q",1],[5,750,1334]],[41,"default","animation",0,false,"animation",110,[110]],[3,"zhidaokuang",6,[[1,-260,[111],112]],[0,"d365myYpJMYoor5UHIFdk/",1],[5,204,172],[0,-49.717,0,0,0,0,1,1,1,1]],[3,"zhidaokuang",6,[[1,-261,[113],114]],[0,"6aI+wPOwBLu497FqXsUrDk",1],[5,204,172],[-224.009,-88.005,0,0,0,0,1,0.5,0.7,1]],[3,"labDesc",6,[[7,"点击左轮拿起",64,80,1,1,1,-262,[115]]],[0,"9cLGpLQPlA57ovNv++XKrt",1],[5,384,100.8],[147.435,68.575,0,0,0,0,1,0.5,0.5,1]],[3,"labDesc",6,[[7,"点击道具使用",64,80,1,1,1,-263,[116]]],[0,"81K3cWEhhIIrUwmbIHhRgX",1],[5,384,100.8],[-120.006,-186.865,0,0,0,0,1,0.5,0.5,1]],[60,"gun",8,10,[[1,-264,[120],121]],[0,"45T7VG4MhG74bc/XZMdB9W",1],[5,575,574],[0,0,0,0,0,-0.25881904510252074,0.9659258262890683,1,1,1],[1,0,0,-30]]],0,[0,9,1,0,0,1,0,0,1,0,6,6,0,10,51,0,11,44,0,12,10,0,13,16,0,14,2,0,15,11,0,7,31,0,16,30,0,0,1,0,-1,50,0,-2,32,0,-3,5,0,-4,10,0,-5,27,0,-6,7,0,-7,9,0,-8,4,0,-9,45,0,-10,26,0,-11,11,0,0,2,0,17,18,0,18,17,0,19,9,0,20,7,0,21,4,0,22,27,0,23,54,0,24,88,0,25,90,0,26,92,0,27,99,0,28,96,0,29,21,0,30,8,0,31,3,0,0,2,0,-1,33,0,-2,8,0,-3,36,0,3,2,0,-5,3,0,-6,89,0,-7,91,0,-8,84,0,3,2,0,6,25,0,32,35,0,33,84,0,34,57,0,8,19,0,0,3,0,3,3,0,-2,56,0,-3,35,0,-4,25,0,-5,17,0,-6,18,0,0,4,0,0,4,0,0,4,0,0,4,0,-1,101,0,-2,102,0,-3,103,0,-4,104,0,-5,28,0,-6,29,0,0,5,0,-1,52,0,-2,53,0,-4,42,0,-5,6,0,-6,16,0,-7,21,0,0,6,0,0,6,0,0,6,0,-1,112,0,-2,113,0,-3,114,0,-4,115,0,0,7,0,0,7,0,0,7,0,-1,105,0,-2,106,0,-3,39,0,35,55,0,36,86,0,8,20,0,0,8,0,-1,34,0,-2,85,0,-3,87,0,3,8,0,0,9,0,0,9,0,-1,40,0,-2,107,0,-3,41,0,0,10,0,0,10,0,-1,43,0,-2,116,0,-3,44,0,0,11,0,0,11,0,0,11,0,-1,47,0,-2,49,0,-1,64,0,-2,65,0,-3,66,0,-4,67,0,-5,68,0,-1,69,0,-2,70,0,-3,71,0,-4,72,0,-5,73,0,-1,74,0,-2,75,0,-3,76,0,-4,77,0,-5,78,0,-1,79,0,-2,80,0,-3,81,0,-4,82,0,-5,83,0,0,16,0,0,16,0,0,16,0,0,16,0,0,17,0,-1,60,0,-2,61,0,0,18,0,-1,62,0,-2,63,0,0,19,0,0,20,0,-1,22,0,-2,23,0,-3,24,0,0,22,0,0,22,0,0,22,0,-1,93,0,0,23,0,0,23,0,0,23,0,-1,94,0,0,24,0,0,24,0,0,24,0,-1,95,0,-1,58,0,-2,59,0,0,26,0,-1,97,0,-2,98,0,0,27,0,-1,100,0,0,28,0,0,28,0,-1,37,0,0,29,0,0,29,0,-1,38,0,37,109,0,0,30,0,-1,108,0,7,111,0,0,31,0,-1,110,0,0,32,0,0,32,0,-1,54,0,0,33,0,-1,55,0,0,34,0,0,35,0,0,37,0,0,37,0,0,38,0,0,38,0,0,39,0,0,39,0,0,40,0,0,40,0,0,41,0,0,41,0,0,43,0,0,43,0,0,44,0,0,45,0,-1,46,0,0,46,0,0,46,0,0,47,0,-1,48,0,0,48,0,0,48,0,0,49,0,0,49,0,-1,51,0,0,52,0,0,53,0,-1,57,0,0,58,0,0,59,0,0,60,0,0,61,0,0,62,0,0,63,0,0,64,0,0,65,0,0,66,0,0,67,0,0,68,0,0,69,0,0,70,0,0,71,0,0,72,0,0,73,0,0,74,0,0,75,0,0,76,0,0,77,0,0,78,0,0,79,0,0,80,0,0,81,0,0,82,0,0,83,0,-1,86,0,-1,88,0,-1,90,0,-1,92,0,0,93,0,0,94,0,0,95,0,-1,99,0,0,100,0,0,101,0,0,102,0,0,103,0,0,104,0,0,105,0,0,106,0,0,107,0,-1,109,0,-1,111,0,0,112,0,0,113,0,0,114,0,0,115,0,0,116,0,38,1,2,3,5,12,3,20,13,3,20,14,3,19,15,3,19,19,3,36,20,3,36,30,3,42,31,3,42,96,0,97,264],[0,0,0,0,0,0,0,0,0,0,0,0,0,0,0,0,0,0,0,0,0,0,0,0,0,0,0,0,0,0,0,0,0,0,0,0,0,0,0,0,0,0,0,0,0,0,0,0,0,0,0,0,0,0,0,0,0,0,0,0,0,0,0,0,0,0,0,0,0,0,0,0,0,0,0,0,0,0,0,0,0,0,0,0,0,0,0,0,0,0,0,0,0,0,0,0,0,0,0,0,0,0,0,0,0,0,0,0,0,0,0,0,0,0,0,0,0,0,0,0,0,0,0,0,0,0,0,0,0,88,90,92],[-1,1,-1,-1,-1,-1,1,-1,-1,-1,1,-1,-1,-1,1,-1,1,-1,1,-1,1,-1,1,-1,1,-1,1,-1,1,-1,1,-1,1,-1,1,-1,1,-1,1,-1,1,-1,1,-1,1,-1,1,-1,1,-1,1,-1,1,-1,1,-1,1,-1,1,-1,-1,-1,-2,-1,-1,-1,1,-1,1,4,-1,-1,1,-1,1,4,-1,-1,1,-1,1,4,-1,-1,-1,-2,-1,1,-1,1,-1,-1,-1,-1,1,-1,-1,1,-1,1,-1,1,-1,-1,-1,-1,1,-1,-1,-1,-1,-1,1,-1,1,-1,-1,-1,-1,1,-1,1,-1,1,-1,1,-1,1,-1,5,5,5],[0,20,0,0,3,0,21,0,0,0,5,0,0,0,5,0,1,0,1,0,1,0,1,0,1,0,2,0,2,0,2,0,2,0,2,0,6,0,1,0,1,0,1,0,1,0,1,0,2,0,2,0,2,0,2,0,2,0,6,3,3,22,23,3,3,0,24,0,25,7,7,0,26,0,27,8,8,0,28,0,29,9,9,0,30,31,0,4,0,4,0,0,0,0,32,0,0,33,0,4,0,4,0,0,0,0,4,0,0,0,3,0,10,0,10,0,0,0,0,4,0,34,0,35,0,36,0,37,0,38,39,40]],[[{"name":"lp_zd","rect":[0,0,144,142],"offset":[0,0],"originalSize":[144,142],"capInsets":[0,0,0,0]}],[1],0,[0],[2],[41]],[[{"name":"emlp_sm2","rect":[0,0,30,29],"offset":[0,0],"originalSize":[30,29],"capInsets":[0,0,0,0]}],[1],0,[0],[2],[42]],[[{"name":"gun1","rect":[0,0,181,111],"offset":[0,0],"originalSize":[181,111],"capInsets":[0,0,0,0]}],[1],0,[0],[2],[43]],[[{"name":"emlp_dhk","rect":[0,0,227,103],"offset":[0,0],"originalSize":[227,103],"capInsets":[0,0,0,0]}],[1],0,[0],[2],[44]],[[{"name":"lp_fx02","rect":[3,2,219,129],"offset":[-0.5,1],"originalSize":[226,135],"capInsets":[0,0,0,0]}],[1],0,[0],[2],[45]],[[[23,"scal",1.0166666666666666,2,{"paths":{"lp_em02":{"props":{"active":[{"frame":0,"value":false},{"frame":0.5,"value":true},{"frame":1.0166666666666666,"value":false}]}}}}]],0,0,[],[],[]],[[[23,"scal1",1,2,{"paths":{"lp_fx02":{"props":{"active":[{"frame":0,"value":false},{"frame":0.5,"value":true},{"frame":1,"value":false}]}}}}]],0,0,[],[],[]],[[{"name":"emlp_btn2","rect":[0,0,217,75],"offset":[0,0],"originalSize":[217,75],"capInsets":[0,0,0,0]}],[1],0,[0],[2],[46]],[[{"name":"lp_fx","rect":[1,0,190,100],"offset":[0.5,0],"originalSize":[191,100],"capInsets":[0,0,0,0]}],[1],0,[0],[2],[47]],[[{"name":"emlp_smdk","rect":[0,0,224,52],"offset":[0,0],"originalSize":[224,52],"capInsets":[0,0,0,0]}],[1],0,[0],[2],[48]],[[{"name":"yz_zd_ks","rect":[0,0,51,52],"offset":[0,0],"originalSize":[51,52],"capInsets":[0,0,0,0]}],[1],0,[0],[2],[49]],[[[23,"scal2",1,2,{"paths":{"lp_fx02":{"props":{"active":[{"frame":0,"value":false},{"frame":0.5,"value":true},{"frame":1,"value":false}]}}}}]],0,0,[],[],[]],[[{"name":"emlp_btn1","rect":[0,0,217,75],"offset":[0,0],"originalSize":[217,75],"capInsets":[0,0,0,0]}],[1],0,[0],[2],[50]],[[{"name":"lp_n02","rect":[3,4,163,172],"offset":[-1.5,-0.5],"originalSize":[172,179],"capInsets":[0,0,0,0]}],[1],0,[0],[2],[51]],[[{"name":"lp_n","rect":[0,0,137,144],"offset":[0,0],"originalSize":[137,144],"capInsets":[0,0,0,0]}],[1],0,[0],[2],[52]]]]