[1,["8b4C1nawJOhp2SZXvCH3Tx"],0,[["sp.SkeletonData",["_name","_atlasText","textureNames","_skeletonJson","textures"],-1,3]],[[0,0,1,2,3,4,5]],[[0,"yd_gq","\nyd_gq.png\nsize: 127,88\nformat: RGBA8888\nfilter: Linear,Linear\nrepeat: none\ngq_jiantou\n  rotate: false\n  xy: 89, 39\n  size: 36, 47\n  orig: 39, 50\n  offset: 1, 1\n  index: -1\ngq_qq\n  rotate: false\n  xy: 2, 2\n  size: 85, 84\n  orig: 88, 87\n  offset: 2, 1\n  index: -1\n",["yd_gq.png"],{"skeleton":{"hash":"DyeevJxfctD/2XY2bXSYOlAaQaQ=","spine":"3.8.75","x":-44,"y":-43.5,"width":88,"height":145.56},"bones":[{"name":"root"},{"name":"all","parent":"root"},{"name":"qq","parent":"all"},{"name":"jt","parent":"all","length":37.25,"rotation":-90,"y":94.02},{"name":"qq2","parent":"all","rotation":180}],"slots":[{"name":"gq_jiantou","bone":"jt","attachment":"gq_jiantou"},{"name":"gq_qq","bone":"qq","attachment":"gq_qq"},{"name":"gq_qq2","bone":"qq2","attachment":"gq_qq"}],"skins":[{"name":"default","attachments":{"gq_qq":{"gq_qq":{"width":88,"height":87}},"gq_jiantou":{"gq_jiantou":{"x":16.96,"rotation":90,"width":39,"height":50}},"gq_qq2":{"gq_qq":{"width":88,"height":87}}}}],"animations":{"animation":{"slots":{"gq_qq2":{"color":[{"time":0.3333,"color":"ffffffff"},{"time":0.9667,"color":"ffffff00","curve":"stepped"},{"time":1,"color":"ffffff00"},{"time":1.6667,"color":"ffffffff"}]},"gq_qq":{"color":[{"color":"ffffff00"},{"time":0.6667,"color":"ffffffff","curve":"stepped"},{"time":1.3333,"color":"ffffffff"},{"time":1.9667,"color":"ffffff00"}]}},"bones":{"qq":{"scale":[{"x":1.4,"y":1.4,"curve":0,"c2":0.36,"c3":0.659},{"time":1.9667,"x":0.8,"y":0.8,"curve":0,"c2":0.36,"c3":0.659},{"time":2,"x":1.4,"y":1.4}]},"jt":{"translate":[{"y":32.12,"curve":0,"c2":0.29,"c3":0.668},{"time":0.1333,"y":-32.12},{"time":1,"y":32.12,"curve":0,"c2":0.29,"c3":0.668},{"time":1.1333,"y":-32.12},{"time":2,"y":32.12}]},"qq2":{"scale":[{"x":0.945,"y":0.945,"curve":0.333,"c2":0.56,"c3":0.729},{"time":0.9667,"x":0.8,"y":0.8,"curve":0,"c2":0.36,"c3":0.659},{"time":1,"x":1.4,"y":1.4,"curve":0,"c2":0.29,"c3":0.445,"c4":0.68},{"time":2,"x":0.945,"y":0.945}]}}}}},[0]]],0,0,[0],[-1],[0]]