[1,["f3m6R0HVdLiL8h/VQnmBQl"],0,[["sp.SkeletonData",["_name","_atlasText","textureNames","_skeletonJson","textures"],-1,3]],[[0,0,1,2,3,4,5]],[[0,"demon_box","\ndemon_box.png\nsize: 1928,1470\nformat: RGBA8888\nfilter: Linear,Linear\nrepeat: none\npic0\n  rotate: false\n  xy: 414, 940\n  size: 416, 528\n  orig: 416, 528\n  offset: 0, 0\n  index: -1\npic1\n  rotate: false\n  xy: 2, 854\n  size: 410, 614\n  orig: 410, 614\n  offset: 0, 0\n  index: -1\npic10\n  rotate: false\n  xy: 404, 428\n  size: 416, 254\n  orig: 416, 254\n  offset: 0, 0\n  index: -1\npic11\n  rotate: true\n  xy: 420, 10\n  size: 416, 254\n  orig: 416, 254\n  offset: 0, 0\n  index: -1\npic12\n  rotate: true\n  xy: 676, 10\n  size: 416, 254\n  orig: 416, 254\n  offset: 0, 0\n  index: -1\npic13\n  rotate: false\n  xy: 832, 507\n  size: 416, 254\n  orig: 416, 254\n  offset: 0, 0\n  index: -1\npic14\n  rotate: false\n  xy: 1250, 579\n  size: 416, 254\n  orig: 416, 254\n  offset: 0, 0\n  index: -1\npic15\n  rotate: true\n  xy: 1668, 635\n  size: 416, 254\n  orig: 416, 254\n  offset: 0, 0\n  index: -1\npic16\n  rotate: true\n  xy: 932, 89\n  size: 416, 254\n  orig: 416, 254\n  offset: 0, 0\n  index: -1\npic17\n  rotate: false\n  xy: 1250, 323\n  size: 416, 254\n  orig: 416, 254\n  offset: 0, 0\n  index: -1\npic18\n  rotate: false\n  xy: 1188, 67\n  size: 416, 254\n  orig: 416, 254\n  offset: 0, 0\n  index: -1\npic19\n  rotate: true\n  xy: 1668, 217\n  size: 416, 254\n  orig: 416, 254\n  offset: 0, 0\n  index: -1\npic2\n  rotate: false\n  xy: 2, 258\n  size: 400, 594\n  orig: 400, 594\n  offset: 0, 0\n  index: -1\npic3\n  rotate: false\n  xy: 832, 1043\n  size: 416, 425\n  orig: 416, 425\n  offset: 0, 0\n  index: -1\npic4\n  rotate: false\n  xy: 1250, 1137\n  size: 416, 331\n  orig: 416, 331\n  offset: 0, 0\n  index: -1\npic5\n  rotate: false\n  xy: 1250, 835\n  size: 416, 300\n  orig: 416, 300\n  offset: 0, 0\n  index: -1\npic6\n  rotate: false\n  xy: 832, 763\n  size: 416, 278\n  orig: 416, 278\n  offset: 0, 0\n  index: -1\npic7\n  rotate: true\n  xy: 1668, 1053\n  size: 415, 258\n  orig: 415, 258\n  offset: 0, 0\n  index: -1\npic8\n  rotate: false\n  xy: 414, 684\n  size: 416, 254\n  orig: 416, 254\n  offset: 0, 0\n  index: -1\npic9\n  rotate: false\n  xy: 2, 2\n  size: 416, 254\n  orig: 416, 254\n  offset: 0, 0\n  index: -1\n",["demon_box.png"],{"skeleton":{"hash":"mYROK8LCH3GsRSvkxNmA45Czzaw=","spine":"3.8.75","x":-375,"y":-264.5,"width":750,"height":1334,"images":"./images/","audio":"D:/1.工作文件/73所有副玩法/恶魔轮盘/箱子/images"},"bones":[{"name":"root"},{"name":"bone","parent":"root"},{"name":"bone2","parent":"bone"},{"name":"box","parent":"bone2"}],"slots":[{"name":"bg","bone":"root"},{"name":"pic19","bone":"box"}],"skins":[{"name":"default","attachments":{"pic19":{"pic0":{"y":73.9,"width":416,"height":528},"pic1":{"y":89.82,"width":410,"height":614},"pic2":{"y":89.82,"width":400,"height":594},"pic3":{"y":64.17,"width":416,"height":425},"pic4":{"y":15.28,"width":416,"height":331},"pic5":{"width":416,"height":300},"pic6":{"width":416,"height":278},"pic7":{"x":0.5,"width":415,"height":258},"pic8":{"width":416,"height":254},"pic9":{"width":416,"height":254},"pic10":{"width":416,"height":254},"pic11":{"width":416,"height":254},"pic12":{"width":416,"height":254},"pic13":{"width":416,"height":254},"pic14":{"width":416,"height":254},"pic15":{"width":416,"height":254},"pic16":{"width":416,"height":254},"pic17":{"width":416,"height":254},"pic18":{"width":416,"height":254},"pic19":{"width":416,"height":254}}}}],"animations":{"close":{"slots":{"pic19":{"attachment":[{"name":"pic0"},{"time":0.0667,"name":"pic1"},{"time":0.1333,"name":"pic2"},{"time":0.2,"name":"pic3"},{"time":0.2667,"name":"pic4"},{"time":0.3333,"name":"pic5"},{"time":0.4,"name":"pic6"},{"time":0.4667,"name":"pic7"},{"time":0.5333,"name":"pic8"},{"time":0.6,"name":"pic9"},{"time":0.6667,"name":"pic10"},{"time":0.7333,"name":"pic11"},{"time":0.8,"name":"pic12"},{"time":0.8667,"name":"pic13"},{"time":0.9333,"name":"pic14"},{"time":1,"name":"pic15"},{"time":1.0667,"name":"pic16"},{"time":1.1333,"name":"pic17"},{"time":1.2,"name":"pic18"},{"time":1.2667,"name":"pic19"},{"time":1.3333,"name":null}]}}},"open":{"slots":{"pic19":{"attachment":[{"name":"pic19"},{"time":0.0667,"name":"pic18"},{"time":0.1333,"name":"pic17"},{"time":0.2,"name":"pic16"},{"time":0.2667,"name":"pic15"},{"time":0.3333,"name":"pic14"},{"time":0.4,"name":"pic13"},{"time":0.4667,"name":"pic12"},{"time":0.5333,"name":"pic11"},{"time":0.6,"name":"pic10"},{"time":0.6667,"name":"pic9"},{"time":0.7333,"name":"pic8"},{"time":0.8,"name":"pic7"},{"time":0.8667,"name":"pic6"},{"time":0.9333,"name":"pic5"},{"time":1,"name":"pic4"},{"time":1.0667,"name":"pic3"},{"time":1.1333,"name":"pic2"},{"time":1.2,"name":"pic1"},{"time":1.2667,"name":"pic0"},{"time":1.3333,"name":"pic0"}]}}}}},[0]]],0,0,[0],[-1],[0]]