[1,["99cfkreINHqbkEh65yh4Fh"],0,[["sp.SkeletonData",["_name","_atlasText","textureNames","_skeletonJson","textures"],-1,3]],[[0,0,1,2,3,4,5]],[[0,"soilder_2","\nsoilder_2.png\nsize: 155,134\nformat: RGBA8888\nfilter: Linear,Linear\nrepeat: none\nts_mz\n  rotate: false\n  xy: 100, 2\n  size: 52, 37\n  orig: 52, 37\n  offset: 0, 0\n  index: -1\nts_s\n  rotate: true\n  xy: 2, 44\n  size: 48, 81\n  orig: 48, 81\n  offset: 0, 0\n  index: -1\nts_t\n  rotate: false\n  xy: 44, 2\n  size: 39, 40\n  orig: 39, 40\n  offset: 0, 0\n  index: -1\nts_wq\n  rotate: true\n  xy: 2, 94\n  size: 38, 121\n  orig: 38, 121\n  offset: 0, 0\n  index: -1\nts_ys\n  rotate: false\n  xy: 2, 2\n  size: 40, 40\n  orig: 40, 40\n  offset: 0, 0\n  index: -1\nts_ysz\n  rotate: true\n  xy: 85, 9\n  size: 11, 13\n  orig: 11, 13\n  offset: 0, 0\n  index: -1\nts_ytj\n  rotate: false\n  xy: 145, 88\n  size: 8, 44\n  orig: 8, 44\n  offset: 0, 0\n  index: -1\nts_zs\n  rotate: true\n  xy: 99, 41\n  size: 35, 54\n  orig: 35, 54\n  offset: 0, 0\n  index: -1\nts_ztj\n  rotate: false\n  xy: 125, 78\n  size: 18, 54\n  orig: 18, 54\n  offset: 0, 0\n  index: -1\nty\n  rotate: true\n  xy: 85, 22\n  size: 70, 12\n  orig: 70, 12\n  offset: 0, 0\n  index: -1\n",["soilder_2.png"],{"skeleton":{"hash":"BibuaDsYGRCmQletwzY7pTfYHk4=","spine":"3.8.75","x":-35.63,"y":-5.17,"width":99.35,"height":138.2},"bones":[{"name":"root","x":1,"y":1,"scaleX":0.5,"scaleY":0.5},{"name":"ts_s","parent":"root","x":-2.03,"y":59.26},{"name":"ts_s2","parent":"ts_s","length":34.86,"rotation":93.29,"y":3.4},{"name":"ts_s3","parent":"ts_s2","length":24.85,"rotation":-6.98,"x":36.88,"y":0.28},{"name":"ts_s4","parent":"ts_s3","length":20.81,"rotation":-14.22,"x":24.85},{"name":"ts_s5","parent":"ts_s4","length":26.48,"rotation":13.58,"x":20.32,"y":-0.37},{"name":"ts_s6","parent":"ts_s4","length":20.96,"rotation":100.79,"x":11.19,"y":3.89},{"name":"ts_zs","parent":"ts_s6","length":53.63,"rotation":74.77,"x":20.81,"y":-0.42},{"name":"ts_zs2","parent":"ts_zs","length":52.81,"rotation":131.13,"x":53,"y":-0.04},{"name":"ts_zs3","parent":"ts_zs2","length":20.05,"rotation":67.22,"x":53,"y":-0.06},{"name":"ts_zs4","parent":"ts_zs2","length":20.58,"rotation":-74.47,"x":-1.8,"y":-4.67},{"name":"ts_zs5","parent":"ts_zs4","length":13.6,"rotation":19.66,"x":21.92,"y":0.54},{"name":"ts_zs6","parent":"ts_zs5","length":12.29,"rotation":14.05,"x":15.72,"y":-0.19},{"name":"ts_zs7","parent":"ts_zs6","length":7.14,"rotation":10.66,"x":14.82,"y":-0.92},{"name":"ts_s7","parent":"ts_s4","length":14.01,"rotation":-70.45,"x":12.71,"y":-0.55},{"name":"ts_ys","parent":"ts_s7","length":29.84,"rotation":-76.48,"x":11.37,"y":-1.13},{"name":"ts_ys2","parent":"ts_ys","length":36.87,"rotation":78.27,"x":30.03,"y":-0.05},{"name":"ts_ys3","parent":"ts_ys2","length":11.02,"rotation":-6.54,"x":37.88,"y":0.14},{"name":"ts_ys4","parent":"ts_ys3","length":50.05,"rotation":81.36,"x":9.88,"y":0.95},{"name":"ts_s8","parent":"ts_s2","length":34.25,"rotation":-147.56,"x":3.13,"y":-11.94},{"name":"ts_s9","parent":"ts_s8","length":36.26,"rotation":-52.07,"x":34.25},{"name":"ts_s10","parent":"ts_s9","length":11.6,"rotation":107.32,"x":34.94,"y":0.24},{"name":"ts_s11","parent":"ts_s2","length":30.17,"rotation":-164.73,"x":8.29,"y":22.02},{"name":"ts_s12","parent":"ts_s11","length":36.1,"rotation":-31.36,"x":30.36,"y":-0.7},{"name":"ts_s13","parent":"ts_s12","length":8.24,"rotation":41.86,"x":35.8,"y":-0.48},{"name":"bone","parent":"root"},{"name":"ts_s14","parent":"ts_s5","length":30.66,"rotation":10.27,"x":27.85,"y":1.48},{"name":"ts_mz","parent":"ts_s14","length":35.04,"rotation":-0.74,"x":30.48,"y":-1.04},{"name":"ts_ztj","parent":"ts_mz","length":35.63,"rotation":173.63,"x":13.34,"y":27.04},{"name":"ts_ztj2","parent":"ts_ztj","length":21.95,"rotation":-7.13,"x":37.11,"y":-0.46},{"name":"ts_ztj3","parent":"ts_ztj2","length":16.9,"rotation":-9.34,"x":22.71,"y":-0.14},{"name":"ts_ztj4","parent":"ts_ztj3","length":13.46,"rotation":-4.73,"x":17.67,"y":-0.01},{"name":"ts_ztj5","parent":"ts_ztj4","length":8.29,"rotation":-20.23,"x":13.68,"y":0.09},{"name":"ts_ytj","parent":"ts_mz","length":32.2,"rotation":-178.23,"x":-0.8,"y":-17.98},{"name":"ts_ytj2","parent":"ts_ytj","length":22.94,"rotation":-6.96,"x":34.87,"y":-0.33},{"name":"ts_ytj3","parent":"ts_ytj2","length":17.08,"rotation":-0.82,"x":26.35,"y":-0.24},{"name":"ts_ytj4","parent":"ts_ytj3","length":8.8,"rotation":-2.36,"x":17.81,"y":0.01},{"name":"z_j","parent":"root","x":-19.69,"y":-0.63},{"name":"z_t","parent":"z_j","x":-3.46,"y":7.48},{"name":"y_j","parent":"root","x":30.87,"y":6.41},{"name":"y_t","parent":"y_j","x":-10.88,"y":-0.64}],"slots":[{"name":"ts_ytj","bone":"ts_ytj","attachment":"ts_ytj"},{"name":"ty","bone":"bone","color":"ffffff7d","attachment":"ty"},{"name":"ts_ys","bone":"ts_ys","attachment":"ts_ys"},{"name":"ts_wq","bone":"ts_ys4","attachment":"ts_wq"},{"name":"ts_ysz","bone":"ts_ys3","attachment":"ts_ysz"},{"name":"ts_s","bone":"ts_s","attachment":"ts_s"},{"name":"ts_zs","bone":"ts_zs","attachment":"ts_zs"},{"name":"ts_t","bone":"ts_s5","attachment":"ts_t"},{"name":"ts_ztj","bone":"ts_ztj","attachment":"ts_ztj"},{"name":"ts_mz","bone":"ts_mz","attachment":"ts_mz"}],"ik":[{"name":"y_j","order":2,"target":"y_j","bones":["ts_s10"]},{"name":"y_t","order":1,"target":"y_t","bendPositive":false,"bones":["ts_s8","ts_s9"]},{"name":"z_j","order":3,"target":"z_j","bones":["ts_s13"]},{"name":"z_t","target":"z_t","bendPositive":false,"bones":["ts_s11","ts_s12"]}],"skins":[{"name":"default","attachments":{"ty":{"ty":{"x":-5.51,"y":-2.45,"scaleX":0.83,"scaleY":0.83,"width":140,"height":24}},"ts_wq":{"ts_wq":{"x":13.48,"y":-6.88,"rotation":-78.24,"width":76,"height":242}},"ts_ys":{"ts_ys":{"type":"mesh","hull":25,"uvs":[0.10086,0.01245,0.16439,0.01198,0.24505,0.09257,0.30543,0.19016,0.419,0.44071,0.52116,0.46506,0.59686,0.4553,0.96274,0.45556,0.98751,0.4808,0.98747,0.58606,0.97168,0.66135,0.93694,0.69635,0.87369,0.71225,0.87354,0.80095,0.83503,0.95016,0.79752,0.9876,0.69705,0.988,0.40617,0.92034,0.31945,0.8916,0.20389,0.7602,0.13194,0.65701,0.05648,0.5055,0.0125,0.32898,0.01234,0.15099,0.02923,0.08445],"triangles":[12,16,17,17,5,6,14,15,16,13,14,16,16,12,13,17,18,5,5,19,4,5,18,19,6,12,17,19,20,4,12,10,11,9,10,12,7,12,6,7,9,12,9,7,8,20,21,4,21,22,3,21,3,4,2,23,24,3,23,2,2,24,1,24,0,1,3,22,23],"vertices":[1,15,-20.16,-7.01,1,1,15,-18.88,-2.15,1,1,15,-11.07,2.33,1,1,15,-2.39,4.92,1,2,15,19.06,8.41,0.82029,16,6.05,12.46,0.17971,2,15,23.03,15.7,0.18582,16,14,10.05,0.81418,2,15,23.85,21.67,0.03168,16,20.01,10.47,0.96832,1,16,48.86,8.72,1,1,16,50.7,6.62,1,1,16,50.2,-1.69,1,1,16,48.6,-7.55,1,1,16,45.69,-10.14,1,1,16,40.63,-11.1,1,1,16,40.2,-18.09,1,1,16,36.46,-29.68,1,1,16,33.33,-32.45,1,1,16,25.4,-32.01,1,1,16,2.78,-25.31,1,1,16,-3.92,-22.63,1,2,15,38.98,-14.59,0.00083,16,-12.42,-11.72,0.99917,2,15,29.63,-17.95,0.14306,16,-17.6,-3.25,0.85694,2,15,16.52,-20.57,0.65043,16,-22.84,9.06,0.34957,2,15,2.15,-20.28,0.93411,16,-25.48,23.18,0.06589,2,15,-11.43,-16.62,0.99695,16,-24.65,37.22,0.00305,2,15,-16.15,-13.96,0.99984,16,-23,42.39,0.00016]}},"ts_ysz":{"ts_ysz":{"x":8.93,"y":-0.3,"rotation":3.12,"width":21,"height":26}},"ts_mz":{"ts_mz":{"x":22.6,"y":9.82,"rotation":-95.19,"width":104,"height":74}},"ts_ytj":{"ts_ytj":{"type":"mesh","hull":14,"uvs":[0.38606,0,0.78605,0.01877,0.93346,0.26788,1,0.41996,1,0.75421,0.9392,0.97903,0.87656,1,0.54723,1,0.5085,0.99995,0,0.88878,0,0.7723,0.04497,0.65512,0.18794,0.375,0.18564,0],"triangles":[6,7,5,5,7,9,7,8,9,5,9,4,9,10,4,10,11,4,11,3,4,11,12,3,12,2,3,2,0,1,0,2,13,2,12,13],"vertices":[1,33,5.1,0.73,1,1,33,7.51,6.88,1,2,33,29.56,6.56,0.94028,34,-6.11,6.19,0.05972,2,33,42.97,6,0.00502,34,7.28,7.26,0.99498,2,35,10.23,7.65,0.98461,36,-7.89,7.32,0.01539,1,36,11.92,7.45,1,1,36,13.82,6.55,1,1,36,14.11,1.29,1,1,36,14.14,0.67,1,2,35,22.3,-8.18,0.11484,36,4.82,-8,0.88516,2,35,12.05,-8.33,0.91287,36,-5.41,-8.57,0.08713,2,34,27.97,-8.02,0.11528,35,1.73,-7.75,0.88472,2,33,37.47,-6.42,0.04303,34,3.32,-5.73,0.95697,1,33,4.71,-2.45,1]}},"ts_ztj":{"ts_ztj":{"type":"mesh","hull":17,"uvs":[0.74882,0.00914,0.89143,0.00907,0.91495,0.01301,0.97258,0.04154,0.97265,0.32036,0.91726,0.62166,0.76919,0.87873,0.71955,0.9304,0.6296,0.95477,0.22632,1,0.0532,1,0,0.98193,0,0.93489,0.23302,0.78766,0.49638,0.54907,0.66496,0.17215,0.66623,0.03718],"triangles":[6,8,13,13,9,12,6,7,8,10,11,12,12,9,10,13,8,9,6,13,5,5,14,4,13,14,5,3,16,0,0,1,3,3,1,2,15,16,3,15,3,4,14,15,4],"vertices":[1,28,-4,-1.85,1,1,28,-4.12,3.29,1,1,28,-3.71,4.14,1,1,28,-0.67,6.28,1,1,28,29.44,6.9,1,2,29,23.96,9.08,0.37062,30,-0.25,9.3,0.62938,3,30,27.82,12.64,0.01735,31,9.07,13.44,0.21381,32,-8.94,10.93,0.76885,2,31,14.91,13.91,0.0351,32,-3.63,13.39,0.9649,2,31,18.58,11.92,0.0021,32,0.5,12.79,0.9979,1,32,13.93,5.41,1,1,32,18.15,0.83,1,2,31,29.92,-7.92,0.00091,32,18.01,-1.9,0.99909,2,31,25.22,-9.86,0.03893,32,14.27,-5.34,0.96107,2,30,24.3,-8.74,0.13796,31,7.32,-8.15,0.86204,2,29,18.4,-7.05,0.88134,30,-3.13,-7.52,0.11866,1,28,13.66,-4.5,1,1,28,-0.91,-4.76,1]}},"ts_s":{"ts_s":{"type":"mesh","hull":45,"uvs":[0.69802,0.00611,0.80098,0.02633,0.82313,0.09203,0.83902,0.13914,0.86103,0.20442,0.88876,0.28665,0.91591,0.36717,0.93747,0.43112,0.94619,0.45699,0.95562,0.52318,0.96673,0.60126,0.97106,0.63166,0.97384,0.66088,0.97791,0.70386,0.98305,0.74401,0.98971,0.79617,0.98972,0.84578,0.98973,0.90978,0.98973,0.94247,0.87353,0.96564,0.72335,0.97993,0.5139,0.9939,0.05079,0.99392,0.0215,0.99128,0,0.96063,0,0.9462,0.00245,0.92989,0.01306,0.85927,0.0282,0.75846,0.04117,0.67211,0.04817,0.62549,0.06804,0.56132,0.0884,0.49559,0.10211,0.45131,0.12315,0.38337,0.14543,0.33284,0.1649,0.28869,0.19223,0.2267,0.2109,0.18437,0.23255,0.15216,0.26251,0.10759,0.28893,0.06827,0.309,0.03843,0.39172,0.01304,0.45241,0.00609],"triangles":[37,38,4,38,39,4,39,40,3,44,3,40,44,40,41,42,44,41,44,42,43,39,3,4,21,22,26,20,21,26,23,26,22,25,26,23,20,26,27,20,27,28,23,24,25,14,29,30,14,30,31,14,31,32,13,32,33,7,33,34,34,35,6,35,36,5,19,17,18,19,16,17,20,16,19,29,14,20,29,20,28,32,13,14,16,20,15,15,20,14,11,12,33,10,11,33,9,10,33,8,9,33,7,8,33,12,13,33,34,6,7,6,35,5,37,4,5,36,37,5,3,44,2,2,0,1,2,44,0],"vertices":[2,5,10.12,-7.5,0.79608,14,10.89,16.52,0.20392,4,5,7.6,-17.6,0.48327,2,85.56,-28.88,0,19,-60.47,58.52,0,14,20.67,12.96,0.51673,5,5,-2.64,-20.39,0.40954,3,41.59,-25.7,0.00332,2,75.03,-30.28,0.02436,19,-46.96,57.46,0.11299,14,22.37,2.48,0.44979,5,5,-9.99,-22.38,0.35668,3,34.22,-27.62,0.0057,2,67.49,-31.29,0.04182,19,-40.29,53.79,0.19401,14,23.6,-5.03,0.40179,5,5,-20.17,-25.15,0.28342,3,24.01,-30.27,0.009,2,57.03,-32.68,0.06603,19,-31.05,48.7,0.30628,14,25.29,-15.44,0.33527,5,5,-32.99,-28.64,0.19115,3,11.15,-33.62,0.01316,2,43.86,-34.44,0.09651,19,-19.41,42.3,0.4477,14,27.43,-28.56,0.25148,5,5,-45.55,-32.06,0.10078,3,-1.44,-36.89,0.01722,2,30.96,-36.16,0.12637,19,-8.01,36.02,0.58619,14,29.52,-41.4,0.16943,5,5,-55.52,-34.77,0.02902,3,-11.44,-39.49,0.02046,2,20.72,-37.53,0.15008,19,1.04,31.04,0.69617,14,31.18,-51.6,0.10427,4,3,-16.86,-41.44,0.02176,2,15.11,-38.8,0.15967,19,4.3,29.1,0.74065,14,31.88,-55.77,0.07792,5,3,-25.86,-42.79,0.01352,2,6,-39.05,0.09916,19,13.79,23.52,0.8361,20,-30.76,-5.09,0.00192,14,33.13,-66.27,0.04931,5,3,-38.11,-45.45,0.00379,2,-6.47,-40.19,0.02779,19,24.5,17.04,0.94867,20,-19.62,0.64,0.00418,14,34.63,-78.7,0.01557,3,19,28.67,14.51,0.99251,20,-14.87,4.52,0.00506,14,35.21,-83.54,0.00244,4,19,32.84,11.86,0.8044,20,-10.84,5.02,0.19337,21,16.96,42.79,0.00077,14,35.7,-88.45,0.00146,4,19,38.55,8.21,0.52775,20,-3.83,8.44,0.47032,21,19.37,34.58,0.00191,14,36.41,-95.65,0.00001,4,19,44.37,3.86,0.29819,20,2.02,10.64,0.64211,21,18.9,28.89,0.05969,14,36.51,-102.47,0.00001,2,20,10.2,13.73,0.86527,21,20.25,19.61,0.13473,2,20,18.14,16.07,0.57239,21,19.78,11.9,0.42761,2,20,28.33,18.97,0.19457,21,19.82,1.32,0.80543,2,20,32.94,20.4,0.00165,21,19.84,-4.09,0.99835,2,20,39.68,10.75,0.08897,21,8.62,-7.65,0.91103,5,20,45.96,-2.43,0.88245,21,-5.83,-9.72,0.01148,23,37.65,39.26,0.03972,22,82.94,13.23,0.00305,24,27.9,28.36,0.06329,4,20,53.78,-21.09,0.35461,23,44.32,20.15,0.13141,22,78.69,-6.55,0.00705,24,20.11,9.68,0.50692,1,24,-1.47,-29.18,1,1,24,-3.21,-31.43,1,2,23,49.99,-29.15,0.00016,24,-8.56,-30.83,0.99984,2,23,47.71,-29.67,0.00124,24,-10.6,-29.69,0.99876,5,3,-96.16,44,0.00004,23,45.33,-30,0.01487,22,46.25,-52.67,0.02998,24,-12.68,-28.31,0.95512,6,34.94,135.16,0,5,3,-85.36,43.23,0.0002,23,34.61,-31.58,0.0739,22,36.98,-47.07,0.15983,24,-21.7,-22.3,0.76606,6,34.82,124.32,0,5,3,-69.93,42.13,0.00043,23,19.31,-33.83,0.15818,22,23.74,-39.08,0.3452,24,-34.58,-13.74,0.49618,6,34.65,108.86,0.00001,5,3,-56.72,41.18,0.00063,23,6.2,-35.76,0.23037,22,12.4,-32.24,0.50399,24,-45.6,-6.4,0.26501,6,34.5,95.61,0.00001,5,3,-49.65,42.84,0.00073,23,-3.97,-36.67,0.26934,22,7.88,-29.94,0.5897,24,-53.77,-0.42,0.14021,6,34.3,87.97,0.00001,6,3,-39.4,40.3,0.08816,2,2.66,45.07,0.00122,23,-10.9,-38.63,0.19817,22,-2.62,-23.58,0.59233,24,-60.23,2.92,0.10308,6,34.65,78.28,0.01704,6,3,-28.97,39.91,0.17771,2,12.97,43.42,0.00247,23,-21.17,-40.5,0.12527,22,-11.74,-18.49,0.59502,24,-69.11,8.4,0.06504,6,34.89,67.84,0.03448,6,3,-21.94,39.65,0.23803,2,19.91,42.31,0.00331,23,-28.08,-41.77,0.07617,22,-17.88,-15.06,0.59684,24,-75.09,12.1,0.03942,6,35.05,60.81,0.04623,6,3,-10.04,38.18,0.3306,2,31.55,39.4,0.00461,23,-43.82,-38.35,0.00081,22,-27.02,-10.64,0.59962,24,-84.56,24.92,0.0001,6,35.25,49.98,0.06427,6,3,-2.62,37.51,0.34593,2,38.84,37.84,0.00344,23,-47.42,-43.85,0.0006,22,-34.12,-4.38,0.46776,24,-90.85,23.49,0.00007,6,34.08,41.39,0.18219,6,3,4.85,36,0.35933,2,46.07,35.43,0.00242,23,-55.03,-43.99,0.00042,22,-40.09,0.37,0.35252,24,-96.6,28.49,0.00005,6,33.01,33.84,0.28526,6,3,15.33,33.88,0.37813,2,56.22,32.05,0.00098,23,-65.73,-44.17,0.00017,22,-48.46,7.02,0.19075,24,-104.67,35.51,0.00002,6,31.52,23.25,0.42995,3,3,22.67,31.85,0.39098,22,-54.9,7.61,0.08026,6,30.34,15.96,0.52876,6,4,-4.58,30.37,0.00918,5,-16.99,35.73,0.00064,3,27.87,30.57,0.30469,22,-58.12,15.67,0.06255,14,-34.93,-5.95,0,6,28.97,10.54,0.62293,6,4,3.27,29.71,0.02189,5,-9.52,33.24,0.00153,3,35.32,28,0.18528,22,-63.58,21.34,0.03804,14,-31.68,1.22,0.00001,6,26.84,2.96,0.75325,6,4,10.19,29.12,0.0331,5,-2.93,31.05,0.00231,3,41.88,25.73,0.07996,22,-68.4,26.35,0.01642,14,-28.81,7.55,0.00002,6,24.97,-3.73,0.8682,4,4,15.45,28.65,0.04161,5,2.08,29.34,0.00291,14,-26.63,12.35,0.00002,6,23.56,-8.81,0.95546,4,4,21.81,22.35,0.15392,5,6.78,21.74,0.03418,14,-18.55,16.24,0.00006,6,16.16,-13.88,0.81183,4,4,24.67,17.16,0.25287,5,8.34,16.01,0.09945,14,-12.68,17.19,0.0001,6,10.51,-15.72,0.64758]}},"ts_t":{"ts_t":{"x":35.1,"y":13.46,"rotation":-85.67,"width":78,"height":80}},"ts_zs":{"ts_zs":{"type":"mesh","hull":37,"uvs":[0.8526,0.84082,0.82876,0.96268,0.8075,0.99126,0.63749,0.99071,0.48594,0.95345,0.24729,0.8754,0.17123,0.84117,0.05151,0.76304,0.03038,0.72778,0.01409,0.66403,0.01398,0.55167,0.01392,0.48596,0.0475,0.33337,0.10401,0.22645,0.16205,0.15241,0.25625,0.06574,0.32961,0.02735,0.38504,0.00924,0.48699,0.00923,0.51415,0.01827,0.54305,0.04604,0.54302,0.22475,0.53749,0.25554,0.52876,0.30415,0.5817,0.29643,0.69468,0.27996,0.76635,0.27974,0.78497,0.20705,0.81027,0.14088,0.8436,0.13048,0.88564,0.13058,0.94747,0.1711,0.98589,0.23291,0.98593,0.42173,0.94562,0.45973,0.8782,0.47633,0.86965,0.5749],"triangles":[29,27,28,31,29,30,33,27,32,29,31,27,31,32,27,33,26,27,0,3,4,1,3,0,2,3,1,4,5,0,36,5,6,0,5,36,9,10,23,8,9,23,6,7,8,8,36,6,33,35,26,34,35,33,35,25,26,8,23,24,35,36,25,36,24,25,24,36,8,18,19,20,20,21,16,21,22,16,20,17,18,20,16,17,22,15,16,22,14,15,22,13,14,22,23,10,22,10,13,10,11,13,11,12,13],"vertices":[4,8,36.29,-47.27,0.0488,11,35.95,13.44,0.0336,12,22.93,8.31,0.26132,13,9.68,7.57,0.65628,1,13,10.6,-5.55,1,1,13,9.74,-8.84,1,2,12,14.97,-12.2,0.22576,13,-1.94,-11.11,0.77424,3,11,22.28,-11.41,0.05901,12,3.64,-12.47,0.76332,13,-13.13,-9.28,0.17766,3,10,30.42,-11.8,0.24878,11,3.85,-14.48,0.66883,12,-14.98,-10.98,0.08238,3,10,24.39,-14.13,0.58106,11,-2.61,-14.65,0.40617,12,-21.29,-9.57,0.01277,2,10,12.77,-16.34,0.97395,11,-14.3,-12.82,0.02605,3,7,75.44,0.56,0.00102,10,8.82,-15.44,0.99515,11,-17.71,-10.64,0.00383,2,7,69.57,-3.09,0.05681,10,2.54,-12.53,0.94319,2,7,58.45,-7.67,0.65207,10,-7.4,-5.76,0.34793,2,7,51.95,-10.35,0.95885,10,-13.21,-1.8,0.04115,1,7,35.96,-14.39,1,1,7,23.87,-15.08,1,1,7,15,-14.34,1,1,7,3.91,-11.77,1,1,7,-1.84,-8.58,1,1,7,-5.11,-5.73,1,1,7,-7.82,0.87,1,1,7,-7.65,3,1,1,7,-5.67,6,1,3,7,12.01,13.27,0.8871,8,36.99,22.11,0.11279,9,14.25,23.35,0.00011,3,7,15.21,14.16,0.7925,8,35.56,19.12,0.20611,9,10.93,23.51,0.00139,3,7,20.25,15.58,0.45236,8,33.31,14.39,0.53162,9,5.7,23.75,0.01602,3,7,18.08,18.69,0.19874,8,37.08,13.98,0.73396,9,6.78,20.11,0.0673,3,7,13.44,25.33,0.03401,8,45.14,13.1,0.64331,9,9.1,12.35,0.32267,3,7,11.51,29.97,0.00548,8,49.9,11.51,0.29142,9,9.47,7.34,0.70309,2,8,53.63,18.45,0.00883,9,17.32,6.59,0.99117,1,9,24.51,5.31,1,1,9,25.78,3.06,1,1,9,25.97,0.13,1,1,9,21.95,-4.49,1,1,9,15.54,-7.64,1,4,8,59.56,-7.82,0.72468,11,17.12,55.19,0.00162,12,14.81,53.38,0.00286,9,-4.61,-9.05,0.27084,5,8,55.58,-10.76,0.90715,11,17.23,50.24,0.00723,12,13.71,48.56,0.01041,13,8.07,48.83,0,9,-8.87,-6.52,0.0752,5,8,50.54,-10.93,0.93026,11,14.46,46.03,0.02955,12,10,45.14,0.03862,13,3.79,46.16,0.00042,9,-10.97,-1.94,0.00115,4,8,46.58,-20.72,0.68275,11,20.18,37.15,0.12551,12,13.39,35.14,0.17988,13,5.27,35.7,0.01187]}}}}],"events":{"attack":{}},"animations":{"attack":{"bones":{"ts_s":{"rotate":[{},{"time":0.2667,"angle":10.04,"curve":"stepped"},{"time":0.4,"angle":10.04},{"time":0.5,"angle":-0.79},{"time":1.1667}],"translate":[{"y":-2.46},{"time":0.2667,"x":-2.44,"y":-4.62},{"time":0.4,"x":-5.12,"y":-4.62},{"time":0.5,"x":12.31,"y":-4.57},{"time":1.1667,"y":-2.46}]},"ts_s2":{"rotate":[{"time":0.4},{"time":0.5,"angle":-9.63},{"time":0.8333,"angle":-11.86},{"time":1.1667}]},"ts_s3":{"rotate":[{"angle":0.07},{"time":0.0667},{"time":0.3333,"angle":8.44},{"time":0.4667,"angle":9.45},{"time":0.5667,"angle":2.57},{"time":0.9,"angle":0.34},{"time":1.1667,"angle":0.07}]},"ts_s4":{"rotate":[{"angle":-0.81},{"time":0.1},{"time":0.3667,"angle":4.86},{"time":0.5,"angle":7.63},{"time":0.6,"angle":-0.47},{"time":0.9333,"angle":-2.7},{"time":1.1667,"angle":-0.81}]},"ts_s5":{"rotate":[{"angle":-0.08},{"time":0.1333},{"time":0.4,"angle":1.42},{"time":0.5333,"angle":2.25},{"time":0.6333,"angle":-0.19,"curve":"stepped"},{"time":0.9667,"angle":-0.19},{"time":1.1667,"angle":-0.08}]},"ts_zs":{"rotate":[{},{"time":0.2667,"angle":-25.65},{"time":0.4,"angle":-29.33},{"time":0.5,"angle":-13.56,"curve":"stepped"},{"time":0.8333,"angle":-13.56},{"time":1.1667}]},"ts_zs2":{"rotate":[{},{"time":0.2667,"angle":-4.85},{"time":0.4,"angle":-11.95},{"time":0.5}]},"ts_zs4":{"rotate":[{"angle":-5.31,"curve":0.381,"c2":0.55,"c3":0.742},{"time":0.1333,"curve":0.25,"c3":0.75},{"time":0.4,"angle":10.9,"curve":0.25,"c3":0.75},{"time":0.5333,"angle":12.59,"curve":0.25,"c3":0.75},{"time":0.6333,"angle":-11.53,"curve":0.25,"c3":0.75},{"time":0.9667,"angle":-14.43,"curve":0.245,"c3":0.637,"c4":0.56},{"time":1.1667,"angle":-5.31}]},"ts_zs5":{"rotate":[{"angle":-9.12,"curve":0.363,"c2":0.44,"c3":0.755},{"time":0.2,"curve":0.25,"c3":0.75},{"time":0.4667,"angle":10.9,"curve":0.25,"c3":0.75},{"time":0.6,"angle":12.59,"curve":0.25,"c3":0.75},{"time":0.7,"angle":-11.53,"curve":0.25,"c3":0.75},{"time":1.0333,"angle":-14.43,"curve":0.258,"c3":0.619,"c4":0.45},{"time":1.1667,"angle":-9.12}]},"ts_zs6":{"rotate":[{"angle":-12.55,"curve":0.32,"c2":0.29,"c3":0.757},{"time":0.2667,"curve":0.25,"c3":0.75},{"time":0.5333,"angle":10.9,"curve":0.25,"c3":0.75},{"time":0.6667,"angle":12.59,"curve":0.25,"c3":0.75},{"time":0.7667,"angle":-11.53,"curve":0.25,"c3":0.75},{"time":1.1,"angle":-14.43,"curve":0.284,"c3":0.625,"c4":0.38},{"time":1.1667,"angle":-12.55}]},"ts_zs7":{"rotate":[{"angle":-14.43,"curve":0.25,"c3":0.75},{"time":0.3333,"curve":0.25,"c3":0.75},{"time":0.6,"angle":10.9,"curve":0.25,"c3":0.75},{"time":0.7333,"angle":12.59,"curve":0.25,"c3":0.75},{"time":0.8333,"angle":-11.53,"curve":0.25,"c3":0.75},{"time":1.1667,"angle":-14.43}]},"ts_ys":{"rotate":[{},{"time":0.2667,"angle":109.19},{"time":0.4,"angle":113.99},{"time":0.4333,"angle":104.71},{"time":0.5,"angle":37.19},{"time":0.8333,"angle":34.29},{"time":1.1667}],"translate":[{"x":8.93,"y":6.66},{"time":0.2667,"x":10.51,"y":8.32,"curve":"stepped"},{"time":0.4,"x":10.51,"y":8.32},{"time":0.5,"x":9.09,"y":6.12,"curve":"stepped"},{"time":0.8333,"x":9.09,"y":6.12},{"time":1.1667,"x":8.93,"y":6.66}]},"ts_ys2":{"rotate":[{},{"time":0.2667,"angle":-36.8},{"time":0.4,"angle":-40.62},{"time":0.4333,"angle":-30.41},{"time":0.5,"angle":-52.62},{"time":0.8333,"angle":-66.32},{"time":1.1667}]},"ts_ys4":{"rotate":[{},{"time":0.2667,"angle":-38.65},{"time":0.4,"angle":-47.79},{"time":0.4333,"angle":-48.75},{"time":0.5,"angle":-55.63},{"time":0.8333,"angle":-45.86},{"time":1.1667}]},"ts_s8":{"rotate":[{"angle":3.99}]},"ts_s9":{"rotate":[{"angle":-6.3}]},"ts_s10":{"rotate":[{"angle":-1.66}]},"ts_s11":{"rotate":[{"angle":4.79}]},"ts_s12":{"rotate":[{"angle":-8.14}]},"ts_s13":{"rotate":[{"angle":0.17}]},"bone":{"scale":[{},{"time":0.3667,"x":0.928,"y":0.928},{"time":0.5,"x":1.115,"y":1.115},{"time":1.1667}]},"ts_ztj":{"rotate":[{"angle":-1.42,"curve":0.381,"c2":0.55,"c3":0.742},{"time":0.1333,"curve":0.25,"c3":0.75},{"time":0.4,"angle":10.26,"curve":0.25,"c3":0.75},{"time":0.5333,"angle":9.91,"curve":0.25,"c3":0.75},{"time":0.6333,"angle":-0.96,"curve":0.25,"c3":0.75},{"time":0.9667,"angle":-3.86,"curve":0.245,"c3":0.637,"c4":0.56},{"time":1.1667,"angle":-1.42}]},"ts_ztj2":{"rotate":[{"angle":-2.44,"curve":0.363,"c2":0.44,"c3":0.755},{"time":0.2},{"time":0.4667,"angle":10.26,"curve":0.25,"c3":0.75},{"time":0.6,"angle":9.91,"curve":0.25,"c3":0.75},{"time":0.7,"angle":-0.96,"curve":0.25,"c3":0.75},{"time":1.0333,"angle":-3.86,"curve":0.258,"c3":0.619,"c4":0.45},{"time":1.1667,"angle":-2.44}]},"ts_ztj3":{"rotate":[{"angle":-3.36,"curve":0.32,"c2":0.29,"c3":0.757},{"time":0.2667},{"time":0.5333,"angle":10.26,"curve":0.25,"c3":0.75},{"time":0.6667,"angle":9.91,"curve":0.25,"c3":0.75},{"time":0.7667,"angle":-0.96,"curve":0.25,"c3":0.75},{"time":1.1,"angle":-3.86,"curve":0.284,"c3":0.625,"c4":0.38},{"time":1.1667,"angle":-3.36}]},"ts_ztj4":{"rotate":[{"curve":0.25,"c3":0.75},{"time":0.2667,"angle":10.26,"curve":0.25,"c3":0.75},{"time":0.4,"angle":9.91,"curve":0.25,"c3":0.75},{"time":0.5,"angle":-0.96,"curve":0.25,"c3":0.75},{"time":0.8333,"angle":-3.86,"curve":0.25,"c3":0.75},{"time":1.1667}]},"ts_ztj5":{"rotate":[{"curve":0.25,"c3":0.75},{"time":0.2667,"angle":10.26,"curve":0.25,"c3":0.75},{"time":0.4,"angle":9.91,"curve":0.25,"c3":0.75},{"time":0.5,"angle":-0.96,"curve":0.25,"c3":0.75},{"time":0.8333,"angle":-3.86,"curve":0.25,"c3":0.75},{"time":1.1667}]},"ts_ytj":{"rotate":[{"angle":-1.89,"curve":0.381,"c2":0.55,"c3":0.742},{"time":0.1333},{"time":0.4,"angle":10.8,"curve":0.25,"c3":0.75},{"time":0.5333,"angle":12.71,"curve":0.25,"c3":0.75},{"time":0.6333,"angle":-2.25,"curve":0.25,"c3":0.75},{"time":0.9667,"angle":-5.15,"curve":0.245,"c3":0.637,"c4":0.56},{"time":1.1667,"angle":-1.89}]},"ts_ytj2":{"rotate":[{"angle":-3.25,"curve":0.363,"c2":0.44,"c3":0.755},{"time":0.2,"curve":0.25,"c3":0.75},{"time":0.4667,"angle":10.8,"curve":0.25,"c3":0.75},{"time":0.6,"angle":12.71,"curve":0.25,"c3":0.75},{"time":0.7,"angle":-2.25,"curve":0.25,"c3":0.75},{"time":1.0333,"angle":-5.15,"curve":0.258,"c3":0.619,"c4":0.45},{"time":1.1667,"angle":-3.25}]},"ts_ytj3":{"rotate":[{"angle":-4.48,"curve":0.32,"c2":0.29,"c3":0.757},{"time":0.2667,"curve":0.25,"c3":0.75},{"time":0.5333,"angle":10.8,"curve":0.25,"c3":0.75},{"time":0.6667,"angle":12.71,"curve":0.25,"c3":0.75},{"time":0.7667,"angle":-2.25,"curve":0.25,"c3":0.75},{"time":1.1,"angle":-5.15,"curve":0.284,"c3":0.625,"c4":0.38},{"time":1.1667,"angle":-4.48}]},"ts_ytj4":{"rotate":[{"curve":0.25,"c3":0.75},{"time":0.2667,"angle":10.8,"curve":0.25,"c3":0.75},{"time":0.4,"angle":12.71,"curve":0.25,"c3":0.75},{"time":0.5,"angle":-2.25,"curve":0.25,"c3":0.75},{"time":0.8333,"angle":-5.15,"curve":0.25,"c3":0.75},{"time":1.1667}]},"z_j":{"rotate":[{},{"time":0.5,"angle":-14.68},{"time":0.6,"angle":-15.39},{"time":1.1667}],"translate":[{},{"time":0.2667,"x":-8.51,"curve":"stepped"},{"time":0.4,"x":-8.51},{"time":0.5,"x":-9.64},{"time":1.1667}]},"y_j":{"translate":[{},{"time":0.2667,"x":2.69,"curve":"stepped"},{"time":0.4,"x":2.69},{"time":0.5,"x":9.51},{"time":1.1667}]}},"events":[{"time":0.5333,"name":"attack"}]},"die":{"slots":{"ts_wq":{"color":[{"color":"ffffffff"},{"time":0.1667,"color":"ffffff00"}]},"ts_ysz":{"color":[{"color":"ffffffff"},{"time":0.1667,"color":"ffffff00"}]},"ty":{"color":[{"color":"ffffffff"},{"time":0.1667,"color":"ffffff00"}]},"ts_mz":{"color":[{"color":"ffffffff"},{"time":0.1667,"color":"ffffff00"}]},"ts_s":{"color":[{"color":"ffffffff"},{"time":0.1667,"color":"ffffff00"}]},"ts_zs":{"color":[{"color":"ffffffff"},{"time":0.1667,"color":"ffffff00"}]},"ts_ytj":{"color":[{"color":"ffffffff"},{"time":0.1667,"color":"ffffff00"}]},"ts_ys":{"color":[{"color":"ffffffff"},{"time":0.1667,"color":"ffffff00"}]},"ts_t":{"color":[{"color":"ffffffff"},{"time":0.1667,"color":"ffffff00"}]},"ts_ztj":{"color":[{"color":"ffffffff"},{"time":0.1667,"color":"ffffff00"}]}}},"idle":{"bones":{"ts_s":{"translate":[{"curve":0.25,"c3":0.75},{"time":0.8333,"y":-4.08,"curve":0.25,"c3":0.75},{"time":1.6667}]},"ts_s2":{"rotate":[{"angle":0.96,"curve":0.25,"c3":0.75},{"time":0.8333,"angle":-1.47,"curve":0.25,"c3":0.75},{"time":1.6667,"angle":0.96}]},"ts_s3":{"rotate":[{"angle":1.32,"curve":0.345,"c2":0.66,"c3":0.679},{"time":0.0333,"angle":1.35,"curve":0.25,"c3":0.75},{"time":0.8667,"angle":-1.08,"curve":0.248,"c3":0.733,"c4":0.93},{"time":1.6667,"angle":1.32}]},"ts_s4":{"rotate":[{"angle":2.06,"curve":0.355,"c2":0.65,"c3":0.69},{"time":0.0667,"angle":2.13,"curve":0.25,"c3":0.75},{"time":0.9,"angle":-0.3,"curve":0.246,"c3":0.718,"c4":0.86},{"time":1.6667,"angle":2.06}]},"ts_s5":{"rotate":[{"angle":1.13,"curve":0.364,"c2":0.64,"c3":0.7},{"time":0.1,"angle":1.27,"curve":0.25,"c3":0.75},{"time":0.9333,"angle":-1,"curve":0.244,"c3":0.704,"c4":0.81},{"time":1.6667,"angle":1.13}]},"ts_s6":{"translate":[{"x":-0.06,"y":0.29,"curve":0.375,"c2":0.62,"c3":0.716},{"time":0.1667,"curve":0.25,"c3":0.75},{"time":1,"x":-0.42,"y":2.22,"curve":0.243,"c3":0.68,"c4":0.71},{"time":1.6667,"x":-0.06,"y":0.29}]},"ts_zs":{"rotate":[{"angle":-1.08,"curve":0.381,"c2":0.59,"c3":0.728},{"time":0.2333},{"time":1.0667,"angle":-4.97,"curve":0.243,"c3":0.66,"c4":0.64},{"time":1.6667,"angle":-1.08}],"translate":[{"x":0.45,"y":0.08,"curve":0.381,"c2":0.59,"c3":0.728},{"time":0.2333,"curve":0.25,"c3":0.75},{"time":1.0667,"x":2.07,"y":0.36,"curve":0.243,"c3":0.66,"c4":0.64},{"time":1.6667,"x":0.45,"y":0.08}]},"ts_zs2":{"rotate":[{"angle":-1.34,"curve":0.382,"c2":0.56,"c3":0.738},{"time":0.3,"curve":0.25,"c3":0.75},{"time":1.1333,"angle":-4.22,"curve":0.244,"c3":0.644,"c4":0.58},{"time":1.6667,"angle":-1.34}]},"ts_zs3":{"rotate":[{"curve":0.25,"c3":0.75},{"time":0.8333,"angle":5.27,"curve":0.25,"c3":0.75},{"time":1.6667}]},"ts_zs4":{"rotate":[{"angle":-2.76,"curve":0.382,"c2":0.56,"c3":0.738},{"time":0.3,"curve":0.25,"c3":0.75},{"time":1.1333,"angle":-8.69,"curve":0.244,"c3":0.644,"c4":0.58},{"time":1.6667,"angle":-2.76}]},"ts_zs5":{"rotate":[{"angle":-3.66,"curve":0.38,"c2":0.53,"c3":0.746},{"time":0.3667,"curve":0.25,"c3":0.75},{"time":1.2,"angle":-8.69,"curve":0.247,"c3":0.632,"c4":0.53},{"time":1.6667,"angle":-3.66}]},"ts_zs6":{"rotate":[{"angle":-4.57,"curve":0.373,"c2":0.49,"c3":0.751},{"time":0.4333,"curve":0.25,"c3":0.75},{"time":1.2667,"angle":-8.69,"curve":0.251,"c3":0.623,"c4":0.49},{"time":1.6667,"angle":-4.57}]},"ts_zs7":{"rotate":[{"angle":-5.49,"curve":0.363,"c2":0.44,"c3":0.755},{"time":0.5,"curve":0.25,"c3":0.75},{"time":1.3333,"angle":-8.69,"curve":0.258,"c3":0.619,"c4":0.45},{"time":1.6667,"angle":-5.49}]},"ts_s7":{"translate":[{"x":0.43,"y":-1.21,"curve":0.381,"c2":0.59,"c3":0.728},{"time":0.2333,"curve":0.25,"c3":0.75},{"time":1.0667,"x":1.97,"y":-5.55,"curve":0.243,"c3":0.66,"c4":0.64},{"time":1.6667,"x":0.43,"y":-1.21}]},"ts_ys":{"rotate":[{"curve":0.25,"c3":0.75},{"time":0.8333,"angle":1.31,"curve":0.25,"c3":0.75},{"time":1.6667}],"translate":[{"curve":0.25,"c3":0.75},{"time":0.8333,"x":3.9,"y":0.08,"curve":0.25,"c3":0.75},{"time":1.6667}]},"ts_ys2":{"rotate":[{"curve":0.25,"c3":0.75},{"time":0.8333,"angle":10.29,"curve":0.25,"c3":0.75},{"time":1.6667}]},"ts_ys4":{"rotate":[{"curve":0.25,"c3":0.75},{"time":0.8333,"angle":-9.48,"curve":0.25,"c3":0.75},{"time":1.6667}]},"ts_s8":{"rotate":[{"angle":3.99}]},"ts_s9":{"rotate":[{"angle":-6.3}]},"ts_s10":{"rotate":[{"angle":-1.66}]},"ts_s11":{"rotate":[{"angle":4.79}]},"ts_s12":{"rotate":[{"angle":-8.14}]},"ts_s13":{"rotate":[{"angle":0.17}]},"bone":{"scale":[{"curve":0.25,"c3":0.625,"c4":0.5},{"time":0.8333,"x":0.956,"y":0.956,"curve":0.375,"c2":0.5,"c3":0.75},{"time":1.6667}]},"ts_ztj":{"rotate":[{"angle":-1.28,"curve":0.379,"c2":0.6,"c3":0.723},{"time":0.2,"angle":-2.93,"curve":0.25,"c3":0.75},{"time":1.0333,"angle":6.56,"curve":0.242,"c3":0.669,"c4":0.68},{"time":1.6667,"angle":-1.28}]},"ts_ztj2":{"rotate":[{"angle":-0.39,"curve":0.382,"c2":0.58,"c3":0.734},{"time":0.2667,"angle":-2.93,"curve":0.25,"c3":0.75},{"time":1.1,"angle":6.56,"curve":0.243,"c3":0.651,"c4":0.61},{"time":1.6667,"angle":-0.39}]},"ts_ztj3":{"rotate":[{"angle":0.57,"curve":0.381,"c2":0.55,"c3":0.742},{"time":0.3333,"angle":-2.93,"curve":0.25,"c3":0.75},{"time":1.1667,"angle":6.56,"curve":0.245,"c3":0.637,"c4":0.56},{"time":1.6667,"angle":0.57}]},"ts_ztj4":{"rotate":[{"angle":1.57,"curve":0.377,"c2":0.51,"c3":0.749},{"time":0.4,"angle":-2.93,"curve":0.25,"c3":0.75},{"time":1.2333,"angle":6.56,"curve":0.249,"c3":0.627,"c4":0.51},{"time":1.6667,"angle":1.57}]},"ts_ztj5":{"rotate":[{"angle":2.57,"curve":0.368,"c2":0.47,"c3":0.753},{"time":0.4667,"angle":-2.93,"curve":0.25,"c3":0.75},{"time":1.3,"angle":6.56,"curve":0.254,"c3":0.62,"c4":0.47},{"time":1.6667,"angle":2.57}]},"ts_ytj":{"rotate":[{"angle":0.45,"curve":0.379,"c2":0.6,"c3":0.723},{"time":0.2,"angle":-0.84,"curve":0.25,"c3":0.75},{"time":1.0333,"angle":6.61,"curve":0.242,"c3":0.669,"c4":0.68},{"time":1.6667,"angle":0.45}]},"ts_ytj2":{"rotate":[{"angle":1.15,"curve":0.382,"c2":0.58,"c3":0.734},{"time":0.2667,"angle":-0.84,"curve":0.25,"c3":0.75},{"time":1.1,"angle":6.61,"curve":0.243,"c3":0.651,"c4":0.61},{"time":1.6667,"angle":1.15}]},"ts_ytj3":{"rotate":[{"angle":1.9,"curve":0.381,"c2":0.55,"c3":0.742},{"time":0.3333,"angle":-0.84,"curve":0.25,"c3":0.75},{"time":1.1667,"angle":6.61,"curve":0.245,"c3":0.637,"c4":0.56},{"time":1.6667,"angle":1.9}]},"ts_ytj4":{"rotate":[{"angle":2.69,"curve":0.377,"c2":0.51,"c3":0.749},{"time":0.4,"angle":-0.84,"curve":0.25,"c3":0.75},{"time":1.2333,"angle":6.61,"curve":0.249,"c3":0.627,"c4":0.51},{"time":1.6667,"angle":2.69}]}}},"move":{"bones":{"ts_s":{"translate":[{"curve":0.25,"c3":0.75},{"time":0.4333,"y":-4.08,"curve":0.25,"c3":0.75},{"time":0.8333,"curve":0.25,"c3":0.75},{"time":1.2667,"y":-4.08,"curve":0.25,"c3":0.75},{"time":1.6667}]},"ts_s2":{"rotate":[{"angle":0.96,"curve":0.25,"c3":0.75},{"time":0.4333,"angle":-1.47,"curve":0.25,"c3":0.75},{"time":0.8333,"angle":0.96,"curve":0.25,"c3":0.75},{"time":1.2667,"angle":-1.47,"curve":0.25,"c3":0.75},{"time":1.6667,"angle":0.96}]},"ts_s3":{"rotate":[{"angle":1.32,"curve":0.345,"c2":0.66,"c3":0.679},{"time":0.0333,"angle":1.35,"curve":0.25,"c3":0.75},{"time":0.4333,"angle":-1.08,"curve":0.248,"c3":0.733,"c4":0.93},{"time":0.8333,"angle":1.32,"curve":0.345,"c2":0.66,"c3":0.679},{"time":0.8667,"angle":1.35,"curve":0.25,"c3":0.75},{"time":1.2667,"angle":-1.08,"curve":0.248,"c3":0.733,"c4":0.93},{"time":1.6667,"angle":1.32}]},"ts_s4":{"rotate":[{"angle":2.06,"curve":0.355,"c2":0.65,"c3":0.69},{"time":0.0333,"angle":2.13,"curve":0.25,"c3":0.75},{"time":0.4667,"angle":-0.3,"curve":0.246,"c3":0.718,"c4":0.86},{"time":0.8333,"angle":2.06,"curve":0.355,"c2":0.65,"c3":0.69},{"time":0.8667,"angle":2.13,"curve":0.25,"c3":0.75},{"time":1.3,"angle":-0.3,"curve":0.246,"c3":0.718,"c4":0.86},{"time":1.6667,"angle":2.06}]},"ts_s5":{"rotate":[{"angle":1.13,"curve":0.364,"c2":0.64,"c3":0.7},{"time":0.0667,"angle":1.27,"curve":0.25,"c3":0.75},{"time":0.4667,"angle":-1,"curve":0.244,"c3":0.704,"c4":0.81},{"time":0.8333,"angle":1.13,"curve":0.364,"c2":0.64,"c3":0.7},{"time":0.9,"angle":1.27,"curve":0.25,"c3":0.75},{"time":1.3,"angle":-1,"curve":0.244,"c3":0.704,"c4":0.81},{"time":1.6667,"angle":1.13}]},"ts_s6":{"translate":[{"x":-0.06,"y":0.29,"curve":0.375,"c2":0.62,"c3":0.716},{"time":0.1,"curve":0.25,"c3":0.75},{"time":0.5,"x":-0.42,"y":2.22,"curve":0.243,"c3":0.68,"c4":0.71},{"time":0.8333,"x":-0.06,"y":0.29,"curve":0.375,"c2":0.62,"c3":0.716},{"time":0.9333,"curve":0.25,"c3":0.75},{"time":1.3333,"x":-0.42,"y":2.22,"curve":0.243,"c3":0.68,"c4":0.71},{"time":1.6667,"x":-0.06,"y":0.29}]},"ts_zs":{"rotate":[{"angle":-1.08,"curve":0.381,"c2":0.59,"c3":0.728},{"time":0.1333},{"time":0.5333,"angle":-4.97,"curve":0.243,"c3":0.66,"c4":0.64},{"time":0.8333,"angle":-1.08,"curve":0.381,"c2":0.59,"c3":0.728},{"time":0.9667},{"time":1.3667,"angle":-4.97,"curve":0.243,"c3":0.66,"c4":0.64},{"time":1.6667,"angle":-1.08}],"translate":[{"x":0.45,"y":0.08,"curve":0.381,"c2":0.59,"c3":0.728},{"time":0.1333,"curve":0.25,"c3":0.75},{"time":0.5333,"x":2.07,"y":0.36,"curve":0.243,"c3":0.66,"c4":0.64},{"time":0.8333,"x":0.45,"y":0.08,"curve":0.381,"c2":0.59,"c3":0.728},{"time":0.9667,"curve":0.25,"c3":0.75},{"time":1.3667,"x":2.07,"y":0.36,"curve":0.243,"c3":0.66,"c4":0.64},{"time":1.6667,"x":0.45,"y":0.08}]},"ts_zs2":{"rotate":[{"angle":-1.34,"curve":0.382,"c2":0.56,"c3":0.738},{"time":0.1667,"curve":0.25,"c3":0.75},{"time":0.5667,"angle":-4.22,"curve":0.244,"c3":0.644,"c4":0.58},{"time":0.8333,"angle":-1.34,"curve":0.382,"c2":0.56,"c3":0.738},{"time":1,"curve":0.25,"c3":0.75},{"time":1.4,"angle":-4.22,"curve":0.244,"c3":0.644,"c4":0.58},{"time":1.6667,"angle":-1.34}]},"ts_zs3":{"rotate":[{"curve":0.25,"c3":0.75},{"time":0.4333,"angle":5.27,"curve":0.25,"c3":0.75},{"time":0.8333,"curve":0.25,"c3":0.75},{"time":1.2667,"angle":5.27,"curve":0.25,"c3":0.75},{"time":1.6667}]},"ts_zs4":{"rotate":[{"angle":-2.76,"curve":0.382,"c2":0.56,"c3":0.738},{"time":0.1667,"curve":0.25,"c3":0.75},{"time":0.5667,"angle":-8.69,"curve":0.244,"c3":0.644,"c4":0.58},{"time":0.8333,"angle":-2.76,"curve":0.382,"c2":0.56,"c3":0.738},{"time":1,"curve":0.25,"c3":0.75},{"time":1.4,"angle":-8.69,"curve":0.244,"c3":0.644,"c4":0.58},{"time":1.6667,"angle":-2.76}]},"ts_zs5":{"rotate":[{"angle":-3.66,"curve":0.38,"c2":0.53,"c3":0.746},{"time":0.2,"curve":0.25,"c3":0.75},{"time":0.6,"angle":-8.69,"curve":0.247,"c3":0.632,"c4":0.53},{"time":0.8333,"angle":-3.66,"curve":0.38,"c2":0.53,"c3":0.746},{"time":1.0333,"curve":0.25,"c3":0.75},{"time":1.4333,"angle":-8.69,"curve":0.247,"c3":0.632,"c4":0.53},{"time":1.6667,"angle":-3.66}]},"ts_zs6":{"rotate":[{"angle":-4.57,"curve":0.373,"c2":0.49,"c3":0.751},{"time":0.2333,"curve":0.25,"c3":0.75},{"time":0.6333,"angle":-8.69,"curve":0.251,"c3":0.623,"c4":0.49},{"time":0.8333,"angle":-4.57,"curve":0.373,"c2":0.49,"c3":0.751},{"time":1.0667,"curve":0.25,"c3":0.75},{"time":1.4667,"angle":-8.69,"curve":0.251,"c3":0.623,"c4":0.49},{"time":1.6667,"angle":-4.57}]},"ts_zs7":{"rotate":[{"angle":-5.49,"curve":0.363,"c2":0.44,"c3":0.755},{"time":0.2667,"curve":0.25,"c3":0.75},{"time":0.6667,"angle":-8.69,"curve":0.258,"c3":0.619,"c4":0.45},{"time":0.8333,"angle":-5.49,"curve":0.363,"c2":0.44,"c3":0.755},{"time":1.1,"curve":0.25,"c3":0.75},{"time":1.5,"angle":-8.69,"curve":0.258,"c3":0.619,"c4":0.45},{"time":1.6667,"angle":-5.49}]},"ts_s7":{"translate":[{"x":0.43,"y":-1.21,"curve":0.381,"c2":0.59,"c3":0.728},{"time":0.1333,"curve":0.25,"c3":0.75},{"time":0.5333,"x":1.97,"y":-5.55,"curve":0.243,"c3":0.66,"c4":0.64},{"time":0.8333,"x":0.43,"y":-1.21,"curve":0.381,"c2":0.59,"c3":0.728},{"time":0.9667,"curve":0.25,"c3":0.75},{"time":1.3667,"x":1.97,"y":-5.55,"curve":0.243,"c3":0.66,"c4":0.64},{"time":1.6667,"x":0.43,"y":-1.21}]},"ts_ys":{"rotate":[{"curve":0.25,"c3":0.75},{"time":0.4333,"angle":1.31,"curve":0.25,"c3":0.75},{"time":0.8333,"curve":0.25,"c3":0.75},{"time":1.2667,"angle":1.31,"curve":0.25,"c3":0.75},{"time":1.6667}],"translate":[{"curve":0.25,"c3":0.75},{"time":0.4333,"x":3.9,"y":0.08,"curve":0.25,"c3":0.75},{"time":0.8333,"curve":0.25,"c3":0.75},{"time":1.2667,"x":3.9,"y":0.08,"curve":0.25,"c3":0.75},{"time":1.6667}]},"ts_ys2":{"rotate":[{"curve":0.25,"c3":0.75},{"time":0.4333,"angle":10.29,"curve":0.25,"c3":0.75},{"time":0.8333,"curve":0.25,"c3":0.75},{"time":1.2667,"angle":10.29,"curve":0.25,"c3":0.75},{"time":1.6667}]},"ts_ys4":{"rotate":[{"curve":0.25,"c3":0.75},{"time":0.4333,"angle":-9.48,"curve":0.25,"c3":0.75},{"time":0.8333,"curve":0.25,"c3":0.75},{"time":1.2667,"angle":-9.48,"curve":0.25,"c3":0.75},{"time":1.6667}]},"ts_s8":{"rotate":[{"angle":3.99}]},"ts_s9":{"rotate":[{"angle":-6.3}]},"ts_s10":{"rotate":[{"angle":-1.66}]},"ts_s11":{"rotate":[{"angle":4.79}]},"ts_s12":{"rotate":[{"angle":-8.14}]},"ts_s13":{"rotate":[{"angle":0.17}]},"bone":{"scale":[{"curve":0.249,"c3":0.627,"c4":0.51},{"time":0.4333,"x":0.943,"y":0.943,"curve":0.377,"c2":0.51,"c3":0.749},{"time":0.8333,"curve":0.25,"c3":0.75},{"time":1.2333,"x":0.943,"y":0.943,"curve":0.377,"c2":0.51,"c3":0.749},{"time":1.6667}]},"ts_mz":{"rotate":[{"angle":3.37}]},"ts_ztj":{"rotate":[{"angle":0.98,"curve":0.379,"c2":0.6,"c3":0.723},{"time":0.1,"curve":0.25,"c3":0.75},{"time":0.5333,"angle":5.62,"curve":0.242,"c3":0.669,"c4":0.68},{"time":0.8333,"angle":0.98,"curve":0.379,"c2":0.6,"c3":0.723},{"time":0.9333,"curve":0.25,"c3":0.75},{"time":1.3667,"angle":5.62,"curve":0.242,"c3":0.669,"c4":0.68},{"time":1.6667,"angle":0.98}]},"ts_ztj2":{"rotate":[{"angle":3.87,"curve":0.382,"c2":0.58,"c3":0.734},{"time":0.1333,"curve":0.25,"c3":0.75},{"time":0.5667,"angle":14.49,"curve":0.243,"c3":0.651,"c4":0.61},{"time":0.8333,"angle":3.87,"curve":0.382,"c2":0.58,"c3":0.734},{"time":0.9667,"curve":0.25,"c3":0.75},{"time":1.4,"angle":14.49,"curve":0.243,"c3":0.651,"c4":0.61},{"time":1.6667,"angle":3.87}]},"ts_ztj3":{"rotate":[{"angle":5.84,"curve":0.381,"c2":0.55,"c3":0.742},{"time":0.1667,"curve":0.25,"c3":0.75},{"time":0.6,"angle":15.86,"curve":0.245,"c3":0.637,"c4":0.56},{"time":0.8333,"angle":5.84,"curve":0.381,"c2":0.55,"c3":0.742},{"time":1,"curve":0.25,"c3":0.75},{"time":1.4333,"angle":15.86,"curve":0.245,"c3":0.637,"c4":0.56},{"time":1.6667,"angle":5.84}]},"ts_ztj4":{"rotate":[{"angle":9.94,"curve":0.377,"c2":0.51,"c3":0.749},{"time":0.2,"curve":0.25,"c3":0.75},{"time":0.6333,"angle":21,"curve":0.249,"c3":0.627,"c4":0.51},{"time":0.8333,"angle":9.94,"curve":0.377,"c2":0.51,"c3":0.749},{"time":1.0333,"curve":0.25,"c3":0.75},{"time":1.4667,"angle":21,"curve":0.249,"c3":0.627,"c4":0.51},{"time":1.6667,"angle":9.94}]},"ts_ztj5":{"rotate":[{"angle":11.55,"curve":0.368,"c2":0.47,"c3":0.753},{"time":0.2333,"curve":0.25,"c3":0.75},{"time":0.6667,"angle":19.94,"curve":0.254,"c3":0.62,"c4":0.47},{"time":0.8333,"angle":11.55,"curve":0.368,"c2":0.47,"c3":0.753},{"time":1.0667,"curve":0.25,"c3":0.75},{"time":1.5,"angle":19.94,"curve":0.254,"c3":0.62,"c4":0.47},{"time":1.6667,"angle":11.55}]},"ts_ytj":{"rotate":[{"angle":1.2,"curve":0.379,"c2":0.6,"c3":0.723},{"time":0.1,"curve":0.25,"c3":0.75},{"time":0.5333,"angle":6.91,"curve":0.242,"c3":0.669,"c4":0.68},{"time":0.8333,"angle":1.2,"curve":0.379,"c2":0.6,"c3":0.723},{"time":0.9333,"curve":0.25,"c3":0.75},{"time":1.3667,"angle":6.91,"curve":0.242,"c3":0.669,"c4":0.68},{"time":1.6667,"angle":1.2}]},"ts_ytj2":{"rotate":[{"angle":4.18,"curve":0.382,"c2":0.58,"c3":0.734},{"time":0.1333,"curve":0.25,"c3":0.75},{"time":0.5667,"angle":15.66,"curve":0.243,"c3":0.651,"c4":0.61},{"time":0.8333,"angle":4.18,"curve":0.382,"c2":0.58,"c3":0.734},{"time":0.9667,"curve":0.25,"c3":0.75},{"time":1.4,"angle":15.66,"curve":0.243,"c3":0.651,"c4":0.61},{"time":1.6667,"angle":4.18}]},"ts_ytj3":{"rotate":[{"angle":4.17,"curve":0.381,"c2":0.55,"c3":0.742},{"time":0.1667,"curve":0.25,"c3":0.75},{"time":0.6,"angle":11.33,"curve":0.245,"c3":0.637,"c4":0.56},{"time":0.8333,"angle":4.17,"curve":0.381,"c2":0.55,"c3":0.742},{"time":1,"curve":0.25,"c3":0.75},{"time":1.4333,"angle":11.33,"curve":0.245,"c3":0.637,"c4":0.56},{"time":1.6667,"angle":4.17}]},"ts_ytj4":{"rotate":[{"angle":14.24,"curve":0.377,"c2":0.51,"c3":0.749},{"time":0.2,"curve":0.25,"c3":0.75},{"time":0.6333,"angle":30.06,"curve":0.249,"c3":0.627,"c4":0.51},{"time":0.8333,"angle":14.24,"curve":0.377,"c2":0.51,"c3":0.749},{"time":1.0333,"curve":0.25,"c3":0.75},{"time":1.4667,"angle":30.06,"curve":0.249,"c3":0.627,"c4":0.51},{"time":1.6667,"angle":14.24}]},"z_j":{"translate":[{"curve":0.249,"c3":0.627,"c4":0.51},{"time":0.4333,"x":6.94,"y":5.65,"curve":0.377,"c2":0.51,"c3":0.749},{"time":0.8333,"x":13.19,"curve":0.25,"c3":0.75},{"time":1.6667}]},"y_j":{"translate":[{"curve":0.25,"c3":0.75},{"time":0.8333,"x":-6.42,"curve":0.249,"c3":0.627,"c4":0.51},{"time":1.2667,"x":-3.04,"y":4.71,"curve":0.377,"c2":0.51,"c3":0.749},{"time":1.6667}]},"y_t":{"rotate":[{"curve":0.25,"c3":0.75},{"time":0.8333,"angle":-0.22,"curve":0.25,"c3":0.75},{"time":1.6667}]}}}}},[0]]],0,0,[0],[-1],[0]]