[1,["3ew8HKcLJODaRnRVFp+6BK","e1gmHVTMZJZY13CoKSGmuT","ceqTsTDxBJvKmLxDGvQBNu"],["_textureSetter","mateBanner_1","mateBanner_1_e18261d5-4cc6-4965-8d77-0a82921a6b93"],["cc.SpriteFrame",["cc.SpriteAtlas",["_name","_spriteFrames"],2,11]],[[1,0,1,2]],[[[[0,"mateBanner_1.plist",[{},"mateBanner_1",6,0,"mateBanner_1_e18261d5-4cc6-4965-8d77-0a82921a6b93",6,1]]],0,0,[0,0],[1,2],[1,2]],[[{"name":"mateBanner_1_e18261d5-4cc6-4965-8d77-0a82921a6b93","rect":[0,0,235,170],"offset":[0,0],"originalSize":[235,170],"capInsets":[0,0,0,0]}],[0],0,[0],[0],[0]],[[{"name":"mateBanner_1","rect":[0,0,235,170],"offset":[0,0],"originalSize":[235,170],"capInsets":[0,0,0,0]}],[0],0,[0],[0],[0]]]]