[1,["17em5CjV1J6Ko8DfMDF/q6"],0,[["sp.SkeletonData",["_name","_atlasText","textureNames","_skeletonJson","textures"],-1,3]],[[0,0,1,2,3,4,5]],[[0,"tfccp_chuxian","\ntfccp_chuxian.png\nsize: 615,527\nformat: RGBA8888\nfilter: Linear,Linear\nrepeat: none\nleven_up_light\n  rotate: true\n  xy: 2, 2\n  size: 35, 140\n  orig: 42, 146\n  offset: 4, 3\n  index: -1\nlz_00002\n  rotate: true\n  xy: 558, 109\n  size: 62, 53\n  orig: 150, 120\n  offset: 16, 31\n  index: -1\nlz_00003\n  rotate: false\n  xy: 387, 10\n  size: 77, 68\n  orig: 150, 120\n  offset: 16, 24\n  index: -1\nlz_00004\n  rotate: false\n  xy: 466, 7\n  size: 86, 77\n  orig: 150, 120\n  offset: 17, 21\n  index: -1\nlz_00005\n  rotate: false\n  xy: 461, 86\n  size: 95, 85\n  orig: 150, 120\n  offset: 18, 17\n  index: -1\nlz_00006\n  rotate: true\n  xy: 295, 137\n  size: 103, 90\n  orig: 150, 120\n  offset: 18, 15\n  index: -1\nlz_00007\n  rotate: false\n  xy: 505, 317\n  size: 108, 94\n  orig: 150, 120\n  offset: 18, 13\n  index: -1\nlz_00008\n  rotate: true\n  xy: 515, 413\n  size: 112, 96\n  orig: 150, 120\n  offset: 19, 12\n  index: -1\nlz_00009\n  rotate: true\n  xy: 286, 20\n  size: 115, 99\n  orig: 150, 120\n  offset: 19, 11\n  index: -1\nlz_00010\n  rotate: true\n  xy: 387, 204\n  size: 117, 100\n  orig: 150, 120\n  offset: 19, 10\n  index: -1\nlz_00011\n  rotate: false\n  xy: 173, 138\n  size: 120, 102\n  orig: 150, 120\n  offset: 19, 9\n  index: -1\nlz_00012\n  rotate: false\n  xy: 164, 35\n  size: 120, 101\n  orig: 150, 120\n  offset: 20, 10\n  index: -1\nlz_00013\n  rotate: true\n  xy: 387, 80\n  size: 122, 72\n  orig: 150, 120\n  offset: 20, 11\n  index: -1\nlz_00014\n  rotate: false\n  xy: 489, 245\n  size: 122, 70\n  orig: 150, 120\n  offset: 21, 13\n  index: -1\nlz_00015\n  rotate: false\n  xy: 489, 173\n  size: 95, 70\n  orig: 150, 120\n  offset: 49, 13\n  index: -1\nzl_tx1\n  rotate: false\n  xy: 174, 242\n  size: 143, 78\n  orig: 203, 142\n  offset: 39, 7\n  index: -1\nzl_tx2\n  rotate: false\n  xy: 348, 323\n  size: 155, 96\n  orig: 203, 142\n  offset: 38, 6\n  index: -1\nzl_tx3\n  rotate: false\n  xy: 348, 421\n  size: 165, 104\n  orig: 203, 142\n  offset: 33, 5\n  index: -1\nzl_tx4\n  rotate: false\n  xy: 2, 276\n  size: 170, 120\n  orig: 203, 142\n  offset: 27, 5\n  index: -1\nzl_tx5\n  rotate: false\n  xy: 2, 398\n  size: 172, 127\n  orig: 203, 142\n  offset: 17, 5\n  index: -1\nzl_tx6\n  rotate: false\n  xy: 2, 39\n  size: 160, 119\n  orig: 203, 142\n  offset: 12, 6\n  index: -1\nzl_tx7\n  rotate: false\n  xy: 2, 160\n  size: 169, 114\n  orig: 203, 142\n  offset: 9, 8\n  index: -1\nzl_tx8\n  rotate: false\n  xy: 176, 407\n  size: 170, 118\n  orig: 203, 142\n  offset: 8, 9\n  index: -1\nzl_tx9\n  rotate: false\n  xy: 176, 322\n  size: 155, 83\n  orig: 203, 142\n  offset: 18, 12\n  index: -1\n",["tfccp_chuxian.png"],{"skeleton":{"hash":"nivMapW4WfidnGC72ojRF8L5Nbk=","spine":"3.8.75","x":-29.45,"y":-2.36,"width":56,"height":83,"images":"./images/heal/","audio":""},"bones":[{"name":"root"},{"name":"bone","parent":"root"},{"name":"bone2","parent":"bone"},{"name":"leven_up_light","parent":"bone2"},{"name":"leven_up_light1","parent":"leven_up_light","x":-62.91,"color":"ff0000ff"},{"name":"leven_up_light2","parent":"leven_up_light","x":34.19,"scaleX":0.8,"scaleY":0.7,"color":"ff0000ff"},{"name":"leven_up_light3","parent":"leven_up_light","x":-6.58,"scaleX":0.8,"scaleY":1.05,"color":"ff0000ff"},{"name":"leven_up_light4","parent":"leven_up_light","x":-26.75,"scaleX":0.9,"scaleY":0.8,"color":"ff0000ff"},{"name":"leven_up_light5","parent":"leven_up_light","x":-50.43,"color":"ff0000ff"},{"name":"leven_up_light6","parent":"leven_up_light","x":58.32,"scaleX":1.1,"scaleY":0.9,"color":"ff0000ff"},{"name":"leven_up_light7","parent":"leven_up_light","x":10.18,"color":"ff0000ff"},{"name":"leven_up_light8","parent":"leven_up_light","x":45.87,"scaleX":0.8,"scaleY":0.6,"color":"ff0000ff"},{"name":"leven_up_light9","parent":"leven_up_light","x":23.46,"scaleY":1.2,"color":"ff0000ff"},{"name":"leven_up_light10","parent":"leven_up_light","x":-1.44,"scaleX":1.1,"scaleY":1.4,"color":"ff0000ff"},{"name":"zl_tx1","parent":"bone2"},{"name":"bone3","parent":"bone2"}],"slots":[{"name":"pic1","bone":"root"},{"name":"lz_00002","bone":"bone3","blend":"additive"},{"name":"leven_up_light1","bone":"leven_up_light1","color":"ffffff8b","blend":"additive"},{"name":"leven_up_light2","bone":"leven_up_light2","color":"ffffff8b","blend":"additive"},{"name":"leven_up_light3","bone":"leven_up_light3","color":"ffffff8b","blend":"additive"},{"name":"leven_up_light4","bone":"leven_up_light4","color":"ffffff8b","blend":"additive"},{"name":"leven_up_light5","bone":"leven_up_light5","color":"ffffff8b","blend":"additive"},{"name":"leven_up_light6","bone":"leven_up_light6","color":"ffffff8b","blend":"additive"},{"name":"leven_up_light7","bone":"leven_up_light7","color":"ffffff8b","blend":"additive"},{"name":"leven_up_light8","bone":"leven_up_light8","color":"ffffff8b","blend":"additive"},{"name":"leven_up_light9","bone":"leven_up_light9","color":"ffffff8b","blend":"additive"},{"name":"leven_up_light10","bone":"leven_up_light10","color":"ffffff8b","blend":"additive"},{"name":"zl_tx1","bone":"zl_tx1","blend":"additive"}],"skins":[{"name":"default","attachments":{"lz_00002":{"lz_00002":{"x":57.4,"width":150,"height":120},"lz_00003":{"x":57.4,"width":150,"height":120},"lz_00004":{"x":57.4,"width":150,"height":120},"lz_00005":{"x":57.4,"width":150,"height":120},"lz_00006":{"x":57.4,"width":150,"height":120},"lz_00007":{"x":57.4,"width":150,"height":120},"lz_00008":{"x":57.4,"width":150,"height":120},"lz_00009":{"x":57.4,"width":150,"height":120},"lz_00010":{"x":57.4,"width":150,"height":120},"lz_00011":{"x":57.4,"width":150,"height":120},"lz_00012":{"x":57.4,"width":150,"height":120},"lz_00013":{"x":57.4,"width":150,"height":120},"lz_00014":{"x":57.4,"width":150,"height":120},"lz_00015":{"x":57.4,"width":150,"height":120}},"leven_up_light1":{"leven_up_light":{"width":42,"height":146}},"leven_up_light2":{"leven_up_light":{"width":42,"height":146}},"leven_up_light3":{"leven_up_light":{"width":42,"height":146}},"leven_up_light4":{"leven_up_light":{"width":42,"height":146}},"leven_up_light5":{"leven_up_light":{"width":42,"height":146}},"leven_up_light6":{"leven_up_light":{"width":42,"height":146}},"leven_up_light7":{"leven_up_light":{"width":42,"height":146}},"leven_up_light8":{"leven_up_light":{"width":42,"height":146}},"leven_up_light9":{"leven_up_light":{"width":42,"height":146}},"zl_tx1":{"zl_tx1":{"y":36.46,"width":203,"height":142},"zl_tx2":{"y":36.46,"width":203,"height":142},"zl_tx3":{"y":36.46,"width":203,"height":142},"zl_tx4":{"y":36.46,"width":203,"height":142},"zl_tx5":{"y":36.46,"width":203,"height":142},"zl_tx6":{"y":36.46,"width":203,"height":142},"zl_tx7":{"y":36.46,"width":203,"height":142},"zl_tx8":{"y":36.46,"width":203,"height":142},"zl_tx9":{"y":36.46,"width":203,"height":142}},"leven_up_light10":{"leven_up_light":{"width":42,"height":146}}}}],"animations":{"animation":{"slots":{"leven_up_light9":{"color":[{"time":0.2,"color":"ffffff00","curve":0.25,"c3":0.75},{"time":0.3667,"color":"ffffff8b","curve":0.25,"c3":0.75},{"time":0.6667,"color":"ffffff00"}],"attachment":[{"time":0.2,"name":"leven_up_light"}]},"zl_tx1":{"color":[{"time":0.4667,"color":"ffffffff","curve":0.25,"c3":0.75},{"time":0.6667,"color":"ffffff00"}],"attachment":[{"name":"zl_tx1"},{"time":0.0667,"name":"zl_tx2"},{"time":0.1333,"name":"zl_tx3"},{"time":0.2,"name":"zl_tx4"},{"time":0.2667,"name":"zl_tx5"},{"time":0.3333,"name":"zl_tx6"},{"time":0.4,"name":"zl_tx7"},{"time":0.4667,"name":"zl_tx8"},{"time":0.5333,"name":"zl_tx9"},{"time":0.6667,"name":null}]},"leven_up_light2":{"color":[{"time":0.0667,"color":"ffffff00","curve":0.25,"c3":0.75},{"time":0.1667,"color":"ffffff8b","curve":0.25,"c3":0.75},{"time":0.4667,"color":"ffffff00"}],"attachment":[{"time":0.0667,"name":"leven_up_light"}]},"leven_up_light1":{"color":[{"color":"ffffff00","curve":0.25,"c3":0.75},{"time":0.2667,"color":"ffffff8b","curve":0.25,"c3":0.75},{"time":0.4,"color":"ffffff00"}],"attachment":[{"name":"leven_up_light"}]},"leven_up_light5":{"color":[{"time":0.1,"color":"ffffff00","curve":0.25,"c3":0.75},{"time":0.3333,"color":"ffffff8b","curve":0.25,"c3":0.75},{"time":0.5333,"color":"ffffff00"}],"attachment":[{"time":0.1,"name":"leven_up_light"}]},"leven_up_light7":{"color":[{"time":0.1667,"color":"ffffff00","curve":0.25,"c3":0.75},{"time":0.3667,"color":"ffffff8b","curve":0.25,"c3":0.75},{"time":0.5667,"color":"ffffff00"}],"attachment":[{"time":0.1667,"name":"leven_up_light"}]},"leven_up_light6":{"color":[{"time":0.0667,"color":"ffffff00","curve":0.25,"c3":0.75},{"time":0.2667,"color":"ffffff8b","curve":0.25,"c3":0.75},{"time":0.5333,"color":"ffffff00"}],"attachment":[{"time":0.0667,"name":"leven_up_light"}]},"lz_00002":{"attachment":[{"name":"lz_00002"},{"time":0.0333,"name":"lz_00003"},{"time":0.0667,"name":"lz_00004"},{"time":0.1,"name":"lz_00005"},{"time":0.1333,"name":"lz_00006"},{"time":0.1667,"name":"lz_00007"},{"time":0.2,"name":"lz_00008"},{"time":0.2333,"name":"lz_00009"},{"time":0.2667,"name":"lz_00010"},{"time":0.3,"name":"lz_00011"},{"time":0.3333,"name":"lz_00012"},{"time":0.3667,"name":"lz_00013"},{"time":0.4,"name":"lz_00014"},{"time":0.4333,"name":"lz_00015"},{"time":0.4667,"name":null}]},"leven_up_light8":{"color":[{"color":"ffffff00","curve":0.25,"c3":0.75},{"time":0.2,"color":"ffffff8b","curve":0.25,"c3":0.75},{"time":0.4333,"color":"ffffff00"}],"attachment":[{"name":"leven_up_light"}]},"leven_up_light3":{"color":[{"color":"ffffff00","curve":0.25,"c3":0.75},{"time":0.2667,"color":"ffffff8b","curve":0.25,"c3":0.75},{"time":0.4333,"color":"ffffff00"}],"attachment":[{"name":"leven_up_light"}]},"leven_up_light10":{"color":[{"time":0.0667,"color":"ffffff00","curve":0.25,"c3":0.75},{"time":0.2667,"color":"ffffff8b","curve":0.25,"c3":0.75},{"time":0.4667,"color":"ffffff00"}],"attachment":[{"time":0.0667,"name":"leven_up_light"}]},"leven_up_light4":{"color":[{"color":"ffffff00","curve":0.25,"c3":0.75},{"time":0.2,"color":"ffffff8b","curve":0.25,"c3":0.75},{"time":0.4667,"color":"ffffff00"}],"attachment":[{"name":"leven_up_light"}]}},"bones":{"leven_up_light1":{"translate":[{"curve":0.25,"c3":0.154},{"time":0.4,"y":126.89}],"scale":[{"y":0.5,"curve":0.25,"c3":0.75},{"time":0.2667,"curve":0.25,"c3":0.75},{"time":0.4,"x":0.2,"y":1.2}]},"leven_up_light2":{"translate":[{"time":0.0667,"curve":0.25,"c3":0.154},{"time":0.4667,"y":138.59}],"scale":[{"time":0.0667,"y":0.5,"curve":0.25,"c3":0.75},{"time":0.1667,"curve":0.25,"c3":0.75},{"time":0.4667,"x":0.2,"y":1.2}]},"leven_up_light3":{"translate":[{"curve":0.25,"c3":0.154},{"time":0.4333,"y":141.71}],"scale":[{"y":0.5,"curve":0.25,"c3":0.75},{"time":0.2667,"curve":0.25,"c3":0.75},{"time":0.4333,"x":0.2,"y":1.2}]},"leven_up_light4":{"translate":[{"curve":0.25,"c3":0.154},{"time":0.4667,"y":146.41}],"scale":[{"y":0.5,"curve":0.25,"c3":0.75},{"time":0.2,"curve":0.25,"c3":0.75},{"time":0.4667,"x":0.2,"y":1.2}]},"leven_up_light5":{"translate":[{"time":0.1,"curve":0.25,"c3":0.154},{"time":0.5333,"y":134.45}],"scale":[{"time":0.1,"y":0.5,"curve":0.25,"c3":0.75},{"time":0.3333,"curve":0.25,"c3":0.75},{"time":0.5333,"x":0.2,"y":1.2}]},"leven_up_light6":{"translate":[{"time":0.0667,"curve":0.25,"c3":0.154},{"time":0.5333,"y":120.22}],"scale":[{"time":0.0667,"y":0.5,"curve":0.25,"c3":0.75},{"time":0.2667,"curve":0.25,"c3":0.75},{"time":0.5333,"x":0.2,"y":1.2}]},"leven_up_light7":{"translate":[{"time":0.1667,"curve":0.25,"c3":0.154},{"time":0.5667,"y":133.57}],"scale":[{"time":0.1667,"y":0.5,"curve":0.25,"c3":0.75},{"time":0.3667,"curve":0.25,"c3":0.75},{"time":0.5667,"x":0.2,"y":1.2}]},"leven_up_light8":{"translate":[{"curve":0.25,"c3":0.154},{"time":0.4333,"y":132.24}],"scale":[{"y":0.5,"curve":0.25,"c3":0.75},{"time":0.2,"curve":0.25,"c3":0.75},{"time":0.4333,"x":0.2,"y":1.2}]},"leven_up_light9":{"translate":[{"time":0.2,"curve":0.25,"c3":0.154},{"time":0.6667,"y":137.26}],"scale":[{"time":0.2,"y":0.5,"curve":0.25,"c3":0.75},{"time":0.3667,"curve":0.25,"c3":0.75},{"time":0.6667,"x":0.2,"y":1.2}]},"leven_up_light10":{"translate":[{"time":0.0667,"curve":0.25,"c3":0.154},{"time":0.4667,"y":145.52}],"scale":[{"time":0.0667,"y":0.5,"curve":0.25,"c3":0.75},{"time":0.2667,"curve":0.25,"c3":0.75},{"time":0.4667,"x":0.2,"y":1.2}]},"zl_tx1":{"scale":[{"x":0.8,"y":0.8,"curve":0.25,"c3":0},{"time":0.6667,"x":1.2,"y":1.2}]},"bone2":{"scale":[{"x":0.8,"y":0.8}]},"leven_up_light":{"translate":[{"y":-20.68}]},"bone3":{"rotate":[{"angle":92.17}],"scale":[{"x":0.537,"y":0.537,"curve":0.25,"c3":0.75},{"time":0.1667,"x":1.108,"y":1.108}]}}}}},[0]]],0,0,[0],[-1],[0]]