[1,["70Ty85XQNEQIHYqEF8zWYX","cfdE5QRMhOqLQLcgB9tsJE","a7rGGo7KhMnaCrOHLlVcAT"],["_textureSetter","qipao1","qipao1_cf744e50-44c8-4ea8-b40b-72007db6c244"],["cc.SpriteFrame",["cc.SpriteAtlas",["_name","_spriteFrames"],2,11]],[[1,0,1,2]],[[[[0,"qipao1.plist",[{},"qipao1",6,0,"qipao1_cf744e50-44c8-4ea8-b40b-72007db6c244",6,1]]],0,0,[0,0],[1,2],[1,2]],[[{"name":"qipao1_cf744e50-44c8-4ea8-b40b-72007db6c244","rect":[0,0,86,86],"offset":[-0.5,0],"originalSize":[87,86],"capInsets":[0,0,0,0]}],[0],0,[0],[0],[0]],[[{"name":"qipao1","rect":[0,0,86,86],"offset":[-0.5,0],"originalSize":[87,86],"capInsets":[0,0,0,0]}],[0],0,[0],[0],[0]]]]